{"assets":{"CBDD5B23089DF60DE60F591CF37FF822":{"type":"texture","index":12,"url":{"native":"assets\/4A50A0C0-30D5-43D2-8C00-86972674604A.pdf"},"width":802,"height":539},"371FE67501357F3E8AB21EABAD9AF0C5":{"type":"texture","index":0,"url":{"native":"assets\/4A50A0C0-30D5-43D2-8C00-86972674604A.pdf"},"width":1920,"height":1080},"ABE537E55E4D3A760C0FDB22C2340556":{"type":"texture","index":10,"url":{"native":"assets\/4A50A0C0-30D5-43D2-8C00-86972674604A.pdf"},"width":1060,"height":712},"5E5183275F1F8BA83123FE7F6946803E":{"type":"texture","index":4,"url":{"native":"assets\/4A50A0C0-30D5-43D2-8C00-86972674604A.pdf"},"width":1608,"height":966},"B1212B6D950D4391052A9C47C6D0A889":{"type":"texture","index":8,"url":{"native":"assets\/4A50A0C0-30D5-43D2-8C00-86972674604A.pdf"},"width":561,"height":512},"2AF5D14B5C73FB4641568DEFE2E0953C":{"type":"texture","index":13,"url":{"native":"assets\/4A50A0C0-30D5-43D2-8C00-86972674604A.pdf"},"width":98,"height":48},"E7B509513C785FFB14F4900734FC5E6C":{"type":"texture","index":17,"url":{"native":"assets\/4A50A0C0-30D5-43D2-8C00-86972674604A.pdf"},"width":207,"height":35},"9303FE48D610EF7CDAFEA4BEE56058C4":{"type":"texture","index":14,"url":{"native":"assets\/4A50A0C0-30D5-43D2-8C00-86972674604A.pdf"},"width":294,"height":32},"416F62ED9726381F58EB430DB9989F21":{"type":"texture","index":9,"url":{"native":"assets\/4A50A0C0-30D5-43D2-8C00-86972674604A.pdf"},"width":436,"height":580},"933F848FACCF3FAFF38F72889019B0EB":{"type":"texture","index":3,"url":{"native":"assets\/4A50A0C0-30D5-43D2-8C00-86972674604A.pdf"},"width":968,"height":813},"1D50D4427BE7767B6298F1E7272B7517":{"type":"texture","index":18,"url":{"native":"assets\/4A50A0C0-30D5-43D2-8C00-86972674604A.pdf"},"width":237,"height":48},"0FB273F8C0876C3FC3D36949432391AB":{"type":"texture","index":20,"url":{"native":"assets\/4A50A0C0-30D5-43D2-8C00-86972674604A.pdf"},"width":346,"height":34},"E373C094B507EF76D2FF3D4FBF71E077":{"type":"texture","index":24,"url":{"native":"assets\/4A50A0C0-30D5-43D2-8C00-86972674604A.pdf"},"width":512,"height":513},"E1179C3FB2577AB4FB025FB9EB4E6E83":{"type":"texture","index":19,"url":{"native":"assets\/4A50A0C0-30D5-43D2-8C00-86972674604A.pdf"},"width":237,"height":39},"5455C0F64006A887F0D9A459FADD9818":{"type":"texture","index":2,"url":{"native":"assets\/4A50A0C0-30D5-43D2-8C00-86972674604A.pdf"},"width":99,"height":55},"AA856C534C8DDB31360A067749ADAA19":{"type":"texture","index":1,"url":{"native":"assets\/4A50A0C0-30D5-43D2-8C00-86972674604A.pdf"},"width":1252,"height":113},"4259FA5E73AE6B87A9955F12C7894657":{"type":"texture","index":5,"url":{"native":"assets\/4A50A0C0-30D5-43D2-8C00-86972674604A.pdf"},"width":669,"height":883},"D1963322FF6D6EB9958D88884468DCB7":{"type":"texture","index":22,"url":{"native":"assets\/4A50A0C0-30D5-43D2-8C00-86972674604A.pdf"},"width":236,"height":48},"CC4B95A4BE772319D0FA1F96092A5C80":{"type":"texture","index":21,"url":{"native":"assets\/4A50A0C0-30D5-43D2-8C00-86972674604A.pdf"},"width":146,"height":47},"4070AE33FA2415694A27DA69F9BAC883":{"type":"texture","index":23,"url":{"native":"assets\/4A50A0C0-30D5-43D2-8C00-86972674604A.pdf"},"width":1608,"height":966},"F2DAB0D8CC060BFE0FF91E035EADADBA":{"type":"texture","index":16,"url":{"native":"assets\/4A50A0C0-30D5-43D2-8C00-86972674604A.pdf"},"width":148,"height":47},"27B373701DB4D31FC4D592353D6E6AAC":{"type":"texture","index":15,"url":{"native":"assets\/4A50A0C0-30D5-43D2-8C00-86972674604A.pdf"},"width":374,"height":37},"78508608182FAB3EE650F9382A01EC41":{"type":"texture","index":7,"url":{"native":"assets\/4A50A0C0-30D5-43D2-8C00-86972674604A.pdf"},"width":769,"height":883},"9BE02F6FC5B80C71FE8949B0FC309186":{"type":"texture","index":6,"url":{"native":"assets\/4A50A0C0-30D5-43D2-8C00-86972674604A.pdf"},"width":513,"height":513},"E9209884329EC7E772D9A62D0141CADC":{"type":"texture","index":11,"url":{"native":"assets\/4A50A0C0-30D5-43D2-8C00-86972674604A.pdf"},"width":826,"height":555}},"events":[{"effects":[{"beginTime":0,"baseLayer":{"animations":[],"initialState":{"affineTransform":[1,0,0,1,0,0],"masksToBounds":false,"rotation":0,"scale":1,"position":{"pointX":254.05859375000003,"pointY":631.92980957031227},"width":99,"sublayerTransform":[1,0,0,0,0,1,0,0,0,0,1,0,0,0,0,1],"contentsRect":{"y":0,"x":0,"width":1,"height":1},"opacity":1,"edgeAntialiasingMask":251658240,"height":55,"hidden":false,"anchorPoint":{"pointX":0.5,"pointY":0.5}},"objectID":"D6EB7CB9-7660-48DB-8152-5E98FB93442C","layers":[{"animations":[],"initialState":{"affineTransform":[1,0,0,1,0,0],"masksToBounds":false,"rotation":0,"scale":1,"position":{"pointX":755.44140625,"pointY":-64.429809570312273},"width":99,"sublayerTransform":[1,0,0,0,0,1,0,0,0,0,1,-0.00035007912466775983,0,0,0,1],"contentsRect":{"y":0,"x":0,"width":1,"height":1},"opacity":1,"edgeAntialiasingMask":251658240,"height":55,"hidden":false,"anchorPoint":{"pointX":7.6307212752525251,"pointY":-1.1714510830965867}},"layers":[{"animations":[{"additive":false,"timeOffset":0,"beginTime":1e-100,"repeatCount":0,"fillMode":"both","duration":0.5,"autoreverses":false,"animations":[{"repeatCount":0,"removedOnCompletion":true,"from":{"scalar":0},"timingFunction":"EaseInEaseOut","additive":false,"timeOffset":0,"autoreverses":false,"property":"opacity","fillMode":"both","duration":0.5,"beginTime":0,"to":{"scalar":1}},{"additive":false,"timeOffset":0,"beginTime":0,"from":{"scalar":false},"repeatCount":0,"fillMode":"forwards","duration":0.5,"autoreverses":false,"property":"hidden","to":{"scalar":false},"removedOnCompletion":true}],"removedOnCompletion":false}],"layers":[],"texturedRectangle":{"singleTextureOpacity":1,"textXHeight":0.55287272727272729,"textBaseline":0.88563265366987753,"isBackgroundTexture":true,"isVerticalText":false,"textColor":[0.97254902124404907,0.97254902124404907,0.94901961088180542,1],"textureType":6},"initialState":{"affineTransform":[1,0,0,1,0,0],"masksToBounds":false,"rotation":0,"scale":1,"position":{"pointX":52.941406249999972,"pointY":43.070190429687727},"width":99,"sublayerTransform":[1,0,0,0,0,1,0,0,0,0,1,0,0,0,0,1],"contentsRect":{"y":0,"x":0,"width":1,"height":1},"opacity":1,"edgeAntialiasingMask":0,"height":55,"hidden":true,"anchorPoint":{"pointX":0.5,"pointY":0.5}},"texture":"5455C0F64006A887F0D9A459FADD9818"}]}]},"effects":[],"duration":0.5,"type":"buildIn","attributes":{"KNBuildCustomAttributesShine":true,"direction":0,"KNBuildCustomAttributesScaleAmount":70},"name":"com.apple.iWork.Keynote.FromDarkness","objectID":"D6EB7CB9-7660-48DB-8152-5E98FB93442C"}],"automaticPlay":false,"hyperlinks":[],"accessibility":[{"text":"Steve_Jobs_flickr_8010717_N02_6216457030_segagman-removebg-preview.png","targetRectangle":{"y":739.24462890625,"x":1765.134033203125,"width":558.36602783203125,"height":509.25540161132812}},{"text":"article-601d0119d549b-removebg-preview.png","targetRectangle":{"y":-139.1433704478394,"x":1840.6102912300748,"width":665.80218365313203,"height":879.57897722380369}},{"text":"images-removebg-preview.png","targetRectangle":{"y":1076.76025390625,"x":1128.74462890625,"width":509.25540161132812,"height":509.25540161132812}},{"text":"C1428466668760-removebg-preview.png","targetRectangle":{"y":-29.595162683956119,"x":-798.78100386235371,"width":965.56194668955106,"height":810.25953923509974}},{"text":"3500-removebg-preview.png","targetRectangle":{"y":817.3206787109375,"x":305.5,"width":1605.0513916015625,"height":963.03082275390625}},{"text":"C1453949543828-removebg-preview.png","targetRectangle":{"y":1026.87939453125,"x":87.8880615234375,"width":1056.32666015625,"height":708.25836181640625}},{"text":"Walt_Disney_1946__cropped2_-removebg-preview.png","targetRectangle":{"y":497.5,"x":-476.5,"width":433,"height":577}},{"text":"想拿學歷以後找好工作。","targetRectangle":{"y":394.5545654296875,"x":206.24609375,"width":1276.2421866506338,"height":151}},{"text":"images-removebg-preview(1).png","targetRectangle":{"y":971.322265625,"x":57,"width":766.8746337890625,"height":880.4246826171875}}],"baseLayer":{"animations":[],"initialState":{"affineTransform":[1,0,0,1,0,0],"masksToBounds":false,"rotation":0,"scale":1,"position":{"pointX":960,"pointY":540},"width":1920,"sublayerTransform":[1,0,0,0,0,1,0,0,0,0,1,0,0,0,0,1],"contentsRect":{"y":0,"x":0,"width":1,"height":1},"opacity":1,"edgeAntialiasingMask":251658240,"height":1080,"hidden":false,"anchorPoint":{"pointX":0.5,"pointY":0.5}},"layers":[{"animations":[],"initialState":{"affineTransform":[1,0,0,1,0,0],"masksToBounds":false,"rotation":0,"scale":1,"position":{"pointX":960,"pointY":540},"width":1920,"sublayerTransform":[1,0,0,0,0,1,0,0,0,0,1,0,0,0,0,1],"contentsRect":{"y":0,"x":0,"width":1,"height":1},"opacity":1,"edgeAntialiasingMask":251658240,"height":1080,"hidden":false,"anchorPoint":{"pointX":0.5,"pointY":0.5}},"layers":[{"animations":[],"initialState":{"affineTransform":[1,0,0,1,0,0],"masksToBounds":false,"rotation":0,"scale":1,"position":{"pointX":960,"pointY":540},"width":1920,"sublayerTransform":[1,0,0,0,0,1,0,0,0,0,1,0,0,0,0,1],"contentsRect":{"y":0,"x":0,"width":1,"height":1},"opacity":1,"edgeAntialiasingMask":251658240,"height":1080,"hidden":false,"anchorPoint":{"pointX":0.5,"pointY":0.5}},"layers":[{"animations":[],"layers":[],"texturedRectangle":{"isBackgroundTexture":true,"singleTextureOpacity":1,"textureType":1,"textBaseline":0,"textXHeight":0,"isVerticalText":false},"initialState":{"affineTransform":[1,0,0,1,0,0],"masksToBounds":false,"rotation":0,"scale":1,"position":{"pointX":960,"pointY":540},"width":1920,"sublayerTransform":[1,0,0,0,0,1,0,0,0,0,1,0,0,0,0,1],"contentsRect":{"y":0,"x":0,"width":1,"height":1},"opacity":1,"edgeAntialiasingMask":0,"height":1080,"hidden":false,"anchorPoint":{"pointX":0.5,"pointY":0.5}},"texture":"371FE67501357F3E8AB21EABAD9AF0C5"}]}]},{"animations":[],"initialState":{"affineTransform":[1,0,0,1,0,0],"masksToBounds":false,"rotation":0,"scale":1,"position":{"pointX":960,"pointY":540},"width":1920,"sublayerTransform":[1,0,0,0,0,1,0,0,0,0,1,0,0,0,0,1],"contentsRect":{"y":0,"x":0,"width":1,"height":1},"opacity":1,"edgeAntialiasingMask":251658240,"height":1080,"hidden":false,"anchorPoint":{"pointX":0.5,"pointY":0.5}},"layers":[{"animations":[],"initialState":{"affineTransform":[1,0,0,1,0,0],"masksToBounds":false,"rotation":0,"scale":1,"position":{"pointX":828.24609375,"pointY":435.05456542968744},"width":1252,"sublayerTransform":[1,0,0,0,0,1,0,0,0,0,1,0,0,0,0,1],"contentsRect":{"y":0,"x":0,"width":1,"height":1},"opacity":1,"edgeAntialiasingMask":251658240,"height":113,"hidden":false,"anchorPoint":{"pointX":0.5,"pointY":0.5}},"layers":[{"animations":[],"layers":[],"texturedRectangle":{"singleTextureOpacity":1,"textXHeight":0.52578816371681414,"textBaseline":0.88536949495298678,"isBackgroundTexture":true,"isVerticalText":false,"textColor":[1,0.47450980544090271,0.7764706015586853,1],"textureType":6},"initialState":{"affineTransform":[1,0,0,1,0,0],"masksToBounds":false,"rotation":0,"scale":1,"position":{"pointX":631.75390625,"pointY":102.94543457031256},"width":1252,"sublayerTransform":[1,0,0,0,0,1,0,0,0,0,1,0,0,0,0,1],"contentsRect":{"y":0,"x":0,"width":1,"height":1},"opacity":1,"edgeAntialiasingMask":0,"height":113,"hidden":false,"anchorPoint":{"pointX":0.5,"pointY":0.5}},"texture":"AA856C534C8DDB31360A067749ADAA19"}]}]},{"animations":[],"initialState":{"affineTransform":[1,0,0,1,0,0],"masksToBounds":false,"rotation":0,"scale":1,"position":{"pointX":960,"pointY":540},"width":1920,"sublayerTransform":[1,0,0,0,0,1,0,0,0,0,1,0,0,0,0,1],"contentsRect":{"y":0,"x":0,"width":1,"height":1},"opacity":1,"edgeAntialiasingMask":251658240,"height":1080,"hidden":false,"anchorPoint":{"pointX":0.5,"pointY":0.5}},"layers":[{"animations":[],"initialState":{"affineTransform":[1,0,0,1,0,0],"masksToBounds":false,"rotation":0,"scale":1,"position":{"pointX":254.05859375000003,"pointY":631.92980957031227},"width":99,"sublayerTransform":[1,0,0,0,0,1,0,0,0,0,1,0,0,0,0,1],"contentsRect":{"y":0,"x":0,"width":1,"height":1},"opacity":1,"edgeAntialiasingMask":251658240,"height":55,"hidden":false,"anchorPoint":{"pointX":0.5,"pointY":0.5}},"objectID":"D6EB7CB9-7660-48DB-8152-5E98FB93442C","layers":[{"animations":[],"layers":[],"texturedRectangle":{"singleTextureOpacity":1,"textXHeight":0.55287272727272729,"textBaseline":0.88563265366987753,"isBackgroundTexture":true,"isVerticalText":false,"textColor":[0.97254902124404907,0.97254902124404907,0.94901961088180542,1],"textureType":6},"initialState":{"affineTransform":[1,0,0,1,0,0],"masksToBounds":false,"rotation":0,"scale":1,"position":{"pointX":52.941406249999972,"pointY":43.070190429687727},"width":99,"sublayerTransform":[1,0,0,0,0,1,0,0,0,0,1,0,0,0,0,1],"contentsRect":{"y":0,"x":0,"width":1,"height":1},"opacity":1,"edgeAntialiasingMask":0,"height":55,"hidden":true,"anchorPoint":{"pointX":0.5,"pointY":0.5}},"texture":"5455C0F64006A887F0D9A459FADD9818"}]}]},{"animations":[],"initialState":{"affineTransform":[1,0,0,1,0,0],"masksToBounds":false,"rotation":0,"scale":1,"position":{"pointX":960,"pointY":540},"width":1920,"sublayerTransform":[1,0,0,0,0,1,0,0,0,0,1,0,0,0,0,1],"contentsRect":{"y":0,"x":0,"width":1,"height":1},"opacity":1,"edgeAntialiasingMask":251658240,"height":1080,"hidden":false,"anchorPoint":{"pointX":0.5,"pointY":0.5}},"layers":[{"animations":[],"initialState":{"affineTransform":[1,0,0,1,0,0],"masksToBounds":false,"rotation":0,"scale":1,"position":{"pointX":-314.78100386235371,"pointY":376.90483731604388},"width":968,"sublayerTransform":[1,0,0,0,0,1,0,0,0,0,1,0,0,0,0,1],"contentsRect":{"y":0,"x":0,"width":1,"height":1},"opacity":1,"edgeAntialiasingMask":251658240,"height":813,"hidden":false,"anchorPoint":{"pointX":0.5,"pointY":0.5}},"layers":[{"animations":[],"layers":[],"texturedRectangle":{"isBackgroundTexture":true,"singleTextureOpacity":1,"textureType":5,"textBaseline":0,"textXHeight":0,"isVerticalText":false},"initialState":{"affineTransform":[1,0,0,1,0,0],"masksToBounds":false,"rotation":0,"scale":1,"position":{"pointX":482.78100386235371,"pointY":405.09516268395612},"width":968,"sublayerTransform":[1,0,0,0,0,1,0,0,0,0,1,0,0,0,0,1],"contentsRect":{"y":0,"x":0,"width":1,"height":1},"opacity":1,"edgeAntialiasingMask":0,"height":813,"hidden":false,"anchorPoint":{"pointX":0.5,"pointY":0.5}},"texture":"933F848FACCF3FAFF38F72889019B0EB"}]}]},{"animations":[],"initialState":{"affineTransform":[1,0,0,1,0,0],"masksToBounds":false,"rotation":0,"scale":1,"position":{"pointX":960,"pointY":540},"width":1920,"sublayerTransform":[1,0,0,0,0,1,0,0,0,0,1,0,0,0,0,1],"contentsRect":{"y":0,"x":0,"width":1,"height":1},"opacity":1,"edgeAntialiasingMask":251658240,"height":1080,"hidden":false,"anchorPoint":{"pointX":0.5,"pointY":0.5}},"layers":[{"animations":[],"initialState":{"affineTransform":[1,0,0,1,0,0],"masksToBounds":false,"rotation":0,"scale":1,"position":{"pointX":1109.5,"pointY":1300.3206787109375},"width":1608,"sublayerTransform":[1,0,0,0,0,1,0,0,0,0,1,0,0,0,0,1],"contentsRect":{"y":0,"x":0,"width":1,"height":1},"opacity":1,"edgeAntialiasingMask":251658240,"height":966,"hidden":false,"anchorPoint":{"pointX":0.5,"pointY":0.5}},"layers":[{"animations":[],"layers":[],"texturedRectangle":{"isBackgroundTexture":true,"singleTextureOpacity":1,"textureType":5,"textBaseline":0,"textXHeight":0,"isVerticalText":false},"initialState":{"affineTransform":[1,0,0,1,0,0],"masksToBounds":false,"rotation":0,"scale":1,"position":{"pointX":802.5,"pointY":481.6793212890625},"width":1608,"sublayerTransform":[1,0,0,0,0,1,0,0,0,0,1,0,0,0,0,1],"contentsRect":{"y":0,"x":0,"width":1,"height":1},"opacity":1,"edgeAntialiasingMask":0,"height":966,"hidden":false,"anchorPoint":{"pointX":0.5,"pointY":0.5}},"texture":"5E5183275F1F8BA83123FE7F6946803E"}]}]},{"animations":[],"initialState":{"affineTransform":[1,0,0,1,0,0],"masksToBounds":false,"rotation":0,"scale":1,"position":{"pointX":960,"pointY":540},"width":1920,"sublayerTransform":[1,0,0,0,0,1,0,0,0,0,1,0,0,0,0,1],"contentsRect":{"y":0,"x":0,"width":1,"height":1},"opacity":1,"edgeAntialiasingMask":251658240,"height":1080,"hidden":false,"anchorPoint":{"pointX":0.5,"pointY":0.5}},"layers":[{"animations":[],"initialState":{"affineTransform":[1,0,0,1,0,0],"masksToBounds":false,"rotation":0,"scale":1,"position":{"pointX":2175.1102912300748,"pointY":302.3566295521606},"width":669,"sublayerTransform":[1,0,0,0,0,1,0,0,0,0,1,0,0,0,0,1],"contentsRect":{"y":0,"x":0,"width":1,"height":1},"opacity":1,"edgeAntialiasingMask":251658240,"height":883,"hidden":false,"anchorPoint":{"pointX":0.5,"pointY":0.5}},"layers":[{"animations":[],"layers":[],"texturedRectangle":{"isBackgroundTexture":true,"singleTextureOpacity":1,"textureType":5,"textBaseline":0,"textXHeight":0,"isVerticalText":false},"initialState":{"affineTransform":[1,0,0,1,0,0],"masksToBounds":false,"rotation":0,"scale":1,"position":{"pointX":332.88970876992516,"pointY":439.6433704478394},"width":669,"sublayerTransform":[1,0,0,0,0,1,0,0,0,0,1,0,0,0,0,1],"contentsRect":{"y":0,"x":0,"width":1,"height":1},"opacity":1,"edgeAntialiasingMask":0,"height":883,"hidden":false,"anchorPoint":{"pointX":0.5,"pointY":0.5}},"texture":"4259FA5E73AE6B87A9955F12C7894657"}]}]},{"animations":[],"initialState":{"affineTransform":[1,0,0,1,0,0],"masksToBounds":false,"rotation":0,"scale":1,"position":{"pointX":960,"pointY":540},"width":1920,"sublayerTransform":[1,0,0,0,0,1,0,0,0,0,1,0,0,0,0,1],"contentsRect":{"y":0,"x":0,"width":1,"height":1},"opacity":1,"edgeAntialiasingMask":251658240,"height":1080,"hidden":false,"anchorPoint":{"pointX":0.5,"pointY":0.5}},"layers":[{"animations":[],"initialState":{"affineTransform":[1,0,0,1,0,0],"masksToBounds":false,"rotation":0,"scale":1,"position":{"pointX":1385.24462890625,"pointY":1333.26025390625},"width":513,"sublayerTransform":[1,0,0,0,0,1,0,0,0,0,1,0,0,0,0,1],"contentsRect":{"y":0,"x":0,"width":1,"height":1},"opacity":1,"edgeAntialiasingMask":251658240,"height":513,"hidden":false,"anchorPoint":{"pointX":0.5,"pointY":0.5}},"layers":[{"animations":[],"layers":[],"texturedRectangle":{"isBackgroundTexture":true,"singleTextureOpacity":1,"textureType":5,"textBaseline":0,"textXHeight":0,"isVerticalText":false},"initialState":{"affineTransform":[1,0,0,1,0,0],"masksToBounds":false,"rotation":0,"scale":1,"position":{"pointX":254.75537109375,"pointY":254.73974609375},"width":513,"sublayerTransform":[1,0,0,0,0,1,0,0,0,0,1,0,0,0,0,1],"contentsRect":{"y":0,"x":0,"width":1,"height":1},"opacity":1,"edgeAntialiasingMask":0,"height":513,"hidden":false,"anchorPoint":{"pointX":0.5,"pointY":0.5}},"texture":"9BE02F6FC5B80C71FE8949B0FC309186"}]}]},{"animations":[],"initialState":{"affineTransform":[1,0,0,1,0,0],"masksToBounds":false,"rotation":0,"scale":1,"position":{"pointX":960,"pointY":540},"width":1920,"sublayerTransform":[1,0,0,0,0,1,0,0,0,0,1,0,0,0,0,1],"contentsRect":{"y":0,"x":0,"width":1,"height":1},"opacity":1,"edgeAntialiasingMask":251658240,"height":1080,"hidden":false,"anchorPoint":{"pointX":0.5,"pointY":0.5}},"layers":[{"animations":[],"initialState":{"affineTransform":[1,0,0,1,0,0],"masksToBounds":false,"rotation":0,"scale":1,"position":{"pointX":441.5,"pointY":1412.822265625},"width":769,"sublayerTransform":[1,0,0,0,0,1,0,0,0,0,1,0,0,0,0,1],"contentsRect":{"y":0,"x":0,"width":1,"height":1},"opacity":1,"edgeAntialiasingMask":251658240,"height":883,"hidden":false,"anchorPoint":{"pointX":0.5,"pointY":0.5}},"layers":[{"animations":[],"layers":[],"texturedRectangle":{"isBackgroundTexture":true,"singleTextureOpacity":1,"textureType":5,"textBaseline":0,"textXHeight":0,"isVerticalText":false},"initialState":{"affineTransform":[1,0,0,1,0,0],"masksToBounds":false,"rotation":0,"scale":1,"position":{"pointX":383.5,"pointY":440.177734375},"width":769,"sublayerTransform":[1,0,0,0,0,1,0,0,0,0,1,0,0,0,0,1],"contentsRect":{"y":0,"x":0,"width":1,"height":1},"opacity":1,"edgeAntialiasingMask":0,"height":883,"hidden":false,"anchorPoint":{"pointX":0.5,"pointY":0.5}},"texture":"78508608182FAB3EE650F9382A01EC41"}]}]},{"animations":[],"initialState":{"affineTransform":[1,0,0,1,0,0],"masksToBounds":false,"rotation":0,"scale":1,"position":{"pointX":960,"pointY":540},"width":1920,"sublayerTransform":[1,0,0,0,0,1,0,0,0,0,1,0,0,0,0,1],"contentsRect":{"y":0,"x":0,"width":1,"height":1},"opacity":1,"edgeAntialiasingMask":251658240,"height":1080,"hidden":false,"anchorPoint":{"pointX":0.5,"pointY":0.5}},"layers":[{"animations":[],"initialState":{"affineTransform":[1,0,0,1,0,0],"masksToBounds":false,"rotation":0,"scale":1,"position":{"pointX":2045.634033203125,"pointY":995.24462890625},"width":561,"sublayerTransform":[1,0,0,0,0,1,0,0,0,0,1,0,0,0,0,1],"contentsRect":{"y":0,"x":0,"width":1,"height":1},"opacity":1,"edgeAntialiasingMask":251658240,"height":512,"hidden":false,"anchorPoint":{"pointX":0.5,"pointY":0.5}},"layers":[{"animations":[],"layers":[],"texturedRectangle":{"isBackgroundTexture":true,"singleTextureOpacity":1,"textureType":5,"textBaseline":0,"textXHeight":0,"isVerticalText":false},"initialState":{"affineTransform":[1,0,0,1,0,0],"masksToBounds":false,"rotation":0,"scale":1,"position":{"pointX":279.365966796875,"pointY":254.75537109375},"width":561,"sublayerTransform":[1,0,0,0,0,1,0,0,0,0,1,0,0,0,0,1],"contentsRect":{"y":0,"x":0,"width":1,"height":1},"opacity":1,"edgeAntialiasingMask":0,"height":512,"hidden":false,"anchorPoint":{"pointX":0.5,"pointY":0.5}},"texture":"B1212B6D950D4391052A9C47C6D0A889"}]}]},{"animations":[],"initialState":{"affineTransform":[1,0,0,1,0,0],"masksToBounds":false,"rotation":0,"scale":1,"position":{"pointX":960,"pointY":540},"width":1920,"sublayerTransform":[1,0,0,0,0,1,0,0,0,0,1,0,0,0,0,1],"contentsRect":{"y":0,"x":0,"width":1,"height":1},"opacity":1,"edgeAntialiasingMask":251658240,"height":1080,"hidden":false,"anchorPoint":{"pointX":0.5,"pointY":0.5}},"layers":[{"animations":[],"initialState":{"affineTransform":[1,0,0,1,0,0],"masksToBounds":false,"rotation":0,"scale":1,"position":{"pointX":-258.5,"pointY":787.5},"width":436,"sublayerTransform":[1,0,0,0,0,1,0,0,0,0,1,0,0,0,0,1],"contentsRect":{"y":0,"x":0,"width":1,"height":1},"opacity":1,"edgeAntialiasingMask":251658240,"height":580,"hidden":false,"anchorPoint":{"pointX":0.5,"pointY":0.5}},"layers":[{"animations":[],"layers":[],"texturedRectangle":{"isBackgroundTexture":true,"singleTextureOpacity":1,"textureType":5,"textBaseline":0,"textXHeight":0,"isVerticalText":false},"initialState":{"affineTransform":[1,0,0,1,0,0],"masksToBounds":false,"rotation":0,"scale":1,"position":{"pointX":216.5,"pointY":288.5},"width":436,"sublayerTransform":[1,0,0,0,0,1,0,0,0,0,1,0,0,0,0,1],"contentsRect":{"y":0,"x":0,"width":1,"height":1},"opacity":1,"edgeAntialiasingMask":0,"height":580,"hidden":false,"anchorPoint":{"pointX":0.5,"pointY":0.5}},"texture":"416F62ED9726381F58EB430DB9989F21"}]}]},{"animations":[],"initialState":{"affineTransform":[1,0,0,1,0,0],"masksToBounds":false,"rotation":0,"scale":1,"position":{"pointX":960,"pointY":540},"width":1920,"sublayerTransform":[1,0,0,0,0,1,0,0,0,0,1,0,0,0,0,1],"contentsRect":{"y":0,"x":0,"width":1,"height":1},"opacity":1,"edgeAntialiasingMask":251658240,"height":1080,"hidden":false,"anchorPoint":{"pointX":0.5,"pointY":0.5}},"layers":[{"animations":[],"initialState":{"affineTransform":[1,0,0,1,0,0],"masksToBounds":false,"rotation":0,"scale":1,"position":{"pointX":617.8880615234375,"pointY":1382.87939453125},"width":1060,"sublayerTransform":[1,0,0,0,0,1,0,0,0,0,1,0,0,0,0,1],"contentsRect":{"y":0,"x":0,"width":1,"height":1},"opacity":1,"edgeAntialiasingMask":251658240,"height":712,"hidden":false,"anchorPoint":{"pointX":0.5,"pointY":0.5}},"layers":[{"animations":[],"layers":[],"texturedRectangle":{"isBackgroundTexture":true,"singleTextureOpacity":1,"textureType":5,"textBaseline":0,"textXHeight":0,"isVerticalText":false},"initialState":{"affineTransform":[1,0,0,1,0,0],"masksToBounds":false,"rotation":0,"scale":1,"position":{"pointX":528.1119384765625,"pointY":354.12060546875},"width":1060,"sublayerTransform":[1,0,0,0,0,1,0,0,0,0,1,0,0,0,0,1],"contentsRect":{"y":0,"x":0,"width":1,"height":1},"opacity":1,"edgeAntialiasingMask":0,"height":712,"hidden":false,"anchorPoint":{"pointX":0.5,"pointY":0.5}},"texture":"ABE537E55E4D3A760C0FDB22C2340556"}]}]}]}},{"effects":[{"beginTime":0,"baseLayer":{"animations":[],"initialState":{"affineTransform":[1,0,0,1,0,0],"masksToBounds":false,"rotation":0,"scale":1,"position":{"pointX":960,"pointY":540},"width":1920,"sublayerTransform":[1,0,0,0,0,1,0,0,0,0,1,0,0,0,0,1],"contentsRect":{"y":0,"x":0,"width":1,"height":1},"opacity":1,"edgeAntialiasingMask":251658240,"height":1080,"hidden":false,"anchorPoint":{"pointX":0.5,"pointY":0.5}},"objectID":"0","layers":[{"animations":[],"initialState":{"affineTransform":[1,0,0,1,0,0],"masksToBounds":false,"rotation":0,"scale":1,"position":{"pointX":960,"pointY":540},"width":1920,"sublayerTransform":[1,0,0,0,0,1,0,0,0,0,1,-0.00035007912466775983,0,0,0,1],"contentsRect":{"y":0,"x":0,"width":1,"height":1},"opacity":1,"edgeAntialiasingMask":251658240,"height":1080,"hidden":false,"anchorPoint":{"pointX":0.5,"pointY":0.5}},"layers":[{"animations":[{"additive":false,"timeOffset":0,"beginTime":0,"repeatCount":0,"fillMode":"both","duration":1,"autoreverses":false,"animations":[{"repeatCount":0,"removedOnCompletion":true,"from":{"scalar":0},"timingFunction":"EaseInEaseOut","additive":false,"timeOffset":0,"autoreverses":false,"property":"zPosition","fillMode":"both","duration":1,"beginTime":0,"to":{"scalar":0}}],"removedOnCompletion":false}],"initialState":{"affineTransform":[1,0,0,1,0,0],"masksToBounds":false,"rotation":0,"scale":1,"position":{"pointX":960,"pointY":540},"width":1920,"sublayerTransform":[1,0,0,0,0,1,0,0,0,0,1,0,0,0,0,1],"contentsRect":{"y":0,"x":0,"width":1,"height":1},"opacity":1,"edgeAntialiasingMask":251658240,"height":1080,"hidden":false,"anchorPoint":{"pointX":0.5,"pointY":0.5}},"layers":[{"animations":[],"layers":[],"texturedRectangle":{"isBackgroundTexture":true,"singleTextureOpacity":1,"textureType":1,"textBaseline":0,"textXHeight":0,"isVerticalText":false},"initialState":{"affineTransform":[1,0,0,1,0,0],"masksToBounds":false,"rotation":0,"scale":1,"position":{"pointX":960,"pointY":540},"width":1920,"sublayerTransform":[1,0,0,0,0,1,0,0,0,0,1,0,0,0,0,1],"contentsRect":{"y":0,"x":0,"width":1,"height":1},"opacity":1,"edgeAntialiasingMask":0,"height":1080,"hidden":false,"anchorPoint":{"pointX":0.5,"pointY":0.5}},"texture":"371FE67501357F3E8AB21EABAD9AF0C5"}]}]},{"animations":[{"additive":false,"timeOffset":0,"beginTime":0,"repeatCount":0,"fillMode":"both","duration":1,"autoreverses":false,"animations":[{"repeatCount":0,"removedOnCompletion":true,"from":{"scalar":0.001},"timingFunction":"EaseInEaseOut","additive":false,"timeOffset":0,"autoreverses":false,"property":"zPosition","fillMode":"both","duration":1,"beginTime":0,"to":{"scalar":0.001}}],"removedOnCompletion":false}],"initialState":{"affineTransform":[1,0,0,1,0,0],"masksToBounds":false,"rotation":0,"scale":1,"position":{"pointX":941.3046875,"pointY":469.5858154296875},"width":1478.1171875,"sublayerTransform":[1,0,0,0,0,1,0,0,0,0,1,0,0,0,0,1],"contentsRect":{"y":0,"x":0,"width":1,"height":1},"opacity":1,"edgeAntialiasingMask":251658240,"height":182.06250000000006,"hidden":false,"anchorPoint":{"pointX":0.5,"pointY":0.5}},"layers":[{"animations":[{"additive":false,"timeOffset":0,"beginTime":0,"repeatCount":0,"fillMode":"both","duration":1,"autoreverses":false,"animations":[{"repeatCount":0,"removedOnCompletion":true,"from":{"scalar":1},"timingFunction":"EaseInEaseOut","additive":false,"timeOffset":0,"autoreverses":false,"property":"opacity","fillMode":"forwards","duration":0.33329999999999999,"beginTime":0,"to":{"scalar":0}},{"additive":false,"timeOffset":0,"beginTime":0.33329999999999999,"from":{"scalar":true},"repeatCount":0,"fillMode":"forwards","duration":0.66670000000000007,"autoreverses":false,"property":"hidden","to":{"scalar":true},"removedOnCompletion":true}],"removedOnCompletion":false}],"layers":[],"texturedRectangle":{"singleTextureOpacity":1,"textXHeight":0.52578816371681414,"textBaseline":0.88536949495298678,"isBackgroundTexture":true,"isVerticalText":false,"textColor":[1,0.47450980544090271,0.7764706015586853,1],"textureType":6},"initialState":{"affineTransform":[1,0,0,1,0,0],"masksToBounds":false,"rotation":0,"scale":1,"position":{"pointX":739.05859375,"pointY":91.031250000000057},"width":1252,"sublayerTransform":[1,0,0,0,0,1,0,0,0,0,1,0,0,0,0,1],"contentsRect":{"y":0,"x":0,"width":1,"height":1},"opacity":1,"edgeAntialiasingMask":0,"height":113,"hidden":false,"anchorPoint":{"pointX":0.58570661940894564,"pointY":0.39456473831581856}},"texture":"AA856C534C8DDB31360A067749ADAA19"}]},{"animations":[{"additive":false,"timeOffset":0,"beginTime":0,"repeatCount":0,"fillMode":"both","duration":1,"autoreverses":false,"animations":[{"repeatCount":0,"removedOnCompletion":true,"from":{"scalar":0.002},"timingFunction":"EaseInEaseOut","additive":false,"timeOffset":0,"autoreverses":false,"property":"zPosition","fillMode":"both","duration":1,"beginTime":0,"to":{"scalar":0.002}}],"removedOnCompletion":false}],"initialState":{"affineTransform":[1,0,0,1,0,0],"masksToBounds":false,"rotation":0,"scale":1,"position":{"pointX":943.6171875,"pointY":688.96887207031239},"width":1478.1171875,"sublayerTransform":[1,0,0,0,0,1,0,0,0,0,1,0,0,0,0,1],"contentsRect":{"y":0,"x":0,"width":1,"height":1},"opacity":1,"edgeAntialiasingMask":251658240,"height":169.07812500000023,"hidden":false,"anchorPoint":{"pointX":0.5,"pointY":0.5}},"layers":[{"animations":[{"additive":false,"timeOffset":0,"beginTime":0,"repeatCount":0,"fillMode":"both","duration":1,"autoreverses":false,"animations":[{"repeatCount":0,"removedOnCompletion":true,"from":{"scalar":1},"timingFunction":"EaseInEaseOut","additive":false,"timeOffset":0,"autoreverses":false,"property":"opacity","fillMode":"forwards","duration":0.33329999999999999,"beginTime":0,"to":{"scalar":0}},{"additive":false,"timeOffset":0,"beginTime":0.33329999999999999,"from":{"scalar":true},"repeatCount":0,"fillMode":"forwards","duration":0.66670000000000007,"autoreverses":false,"property":"hidden","to":{"scalar":true},"removedOnCompletion":true}],"removedOnCompletion":false}],"layers":[],"texturedRectangle":{"singleTextureOpacity":1,"textXHeight":0.55287272727272729,"textBaseline":0.88563265366987753,"isBackgroundTexture":true,"isVerticalText":false,"textColor":[0.97254902124404907,0.97254902124404907,0.94901961088180542,1],"textureType":6},"initialState":{"affineTransform":[1,0,0,1,0,0],"masksToBounds":false,"rotation":0,"scale":1,"position":{"pointX":739.05859375,"pointY":84.539062500000227},"width":99,"sublayerTransform":[1,0,0,0,0,1,0,0,0,0,1,0,0,0,0,1],"contentsRect":{"y":0,"x":0,"width":1,"height":1},"opacity":1,"edgeAntialiasingMask":0,"height":55,"hidden":false,"anchorPoint":{"pointX":7.430476641414141,"pointY":1.2539794921875}},"texture":"5455C0F64006A887F0D9A459FADD9818"}]},{"animations":[{"additive":false,"timeOffset":0,"beginTime":0,"repeatCount":0,"fillMode":"both","duration":1,"autoreverses":false,"animations":[{"repeatCount":0,"removedOnCompletion":true,"from":{"scalar":0.0030000000000000001},"timingFunction":"EaseInEaseOut","additive":false,"timeOffset":0,"autoreverses":false,"property":"zPosition","fillMode":"both","duration":1,"beginTime":0,"to":{"scalar":0.0030000000000000001}}],"removedOnCompletion":false}],"initialState":{"affineTransform":[1,0,0,1,0,0],"masksToBounds":false,"rotation":0,"scale":1,"position":{"pointX":-316.00003051757812,"pointY":375.53460693359375},"width":822.25921630859375,"sublayerTransform":[1,0,0,0,0,1,0,0,0,0,1,0,0,0,0,1],"contentsRect":{"y":0,"x":0,"width":1,"height":1},"opacity":1,"edgeAntialiasingMask":251658240,"height":551.31805419921875,"hidden":false,"anchorPoint":{"pointX":0.5,"pointY":0.5}},"layers":[{"animations":[{"additive":false,"timeOffset":0,"beginTime":0,"repeatCount":0,"fillMode":"both","duration":1,"autoreverses":false,"animations":[{"repeatCount":0,"removedOnCompletion":true,"from":{"texture":"E9209884329EC7E772D9A62D0141CADC"},"timingFunction":"EaseInEaseOut","additive":false,"timeOffset":0,"autoreverses":false,"property":"contents","fillMode":"both","duration":1,"beginTime":0,"to":{"texture":"E9209884329EC7E772D9A62D0141CADC"}},{"additive":false,"timeOffset":0,"beginTime":0,"from":{"scalar":-0.3680793558434321},"repeatCount":0,"fillMode":"both","duration":1,"autoreverses":false,"property":"transform.rotation.z","to":{"scalar":-0.3680793558434321},"removedOnCompletion":true},{"repeatCount":0,"removedOnCompletion":true,"from":{"pointX":0,"pointY":0},"timingFunction":"EaseInEaseOut","additive":false,"timeOffset":0,"autoreverses":false,"property":"transform.translation","fillMode":"both","duration":1,"beginTime":0,"to":{"pointX":684.00000204406251,"pointY":-115.99998901903999}}],"removedOnCompletion":false}],"layers":[],"texturedRectangle":{"isBackgroundTexture":true,"singleTextureOpacity":1,"textureType":5,"textBaseline":0,"textXHeight":0,"isVerticalText":false},"initialState":{"affineTransform":[0.93302016012684175,-0.35982409702086737,0.35982409702086737,0.93302016012684175,0,0],"masksToBounds":false,"rotation":-0.3680793558434321,"scale":1,"position":{"pointX":411.12960815429682,"pointY":275.65902709960938},"width":826,"sublayerTransform":[1,0,0,0,0,1,0,0,0,0,1,0,0,0,0,1],"contentsRect":{"y":0,"x":0,"width":1,"height":1},"opacity":1,"edgeAntialiasingMask":0,"height":555,"hidden":false,"anchorPoint":{"pointX":0.49999996305377942,"pointY":0.50006235483530403}},"texture":"E9209884329EC7E772D9A62D0141CADC"}]},{"animations":[{"additive":false,"timeOffset":0,"beginTime":0,"repeatCount":0,"fillMode":"both","duration":1,"autoreverses":false,"animations":[{"repeatCount":0,"removedOnCompletion":true,"from":{"scalar":0.0040000000000000001},"timingFunction":"EaseInEaseOut","additive":false,"timeOffset":0,"autoreverses":false,"property":"zPosition","fillMode":"both","duration":1,"beginTime":0,"to":{"scalar":0.0040000000000000001}}],"removedOnCompletion":false}],"initialState":{"affineTransform":[1,0,0,1,0,0],"masksToBounds":false,"rotation":0,"scale":1,"position":{"pointX":1108.0256958007812,"pointY":1298.8360900878906},"width":1605.0513916015625,"sublayerTransform":[1,0,0,0,0,1,0,0,0,0,1,0,0,0,0,1],"contentsRect":{"y":0,"x":0,"width":1,"height":1},"opacity":1,"edgeAntialiasingMask":251658240,"height":963.03082275390625,"hidden":false,"anchorPoint":{"pointX":0.5,"pointY":0.5}},"layers":[{"animations":[{"additive":false,"timeOffset":0,"beginTime":0,"repeatCount":0,"fillMode":"both","duration":1,"autoreverses":false,"animations":[{"repeatCount":0,"removedOnCompletion":true,"from":{"texture":"5E5183275F1F8BA83123FE7F6946803E"},"timingFunction":"EaseInEaseOut","additive":false,"timeOffset":0,"autoreverses":false,"property":"contents","fillMode":"both","duration":1,"beginTime":0,"to":{"texture":"4070AE33FA2415694A27DA69F9BAC883"}},{"repeatCount":0,"removedOnCompletion":true,"from":{"pointX":0,"pointY":0},"timingFunction":"EaseInEaseOut","additive":false,"timeOffset":0,"autoreverses":false,"property":"transform.translation","fillMode":"both","duration":1,"beginTime":0,"to":{"pointX":16,"pointY":-792}}],"removedOnCompletion":false}],"layers":[],"texturedRectangle":{"isBackgroundTexture":true,"singleTextureOpacity":1,"textureType":5,"textBaseline":0,"textXHeight":0,"isVerticalText":false},"initialState":{"affineTransform":[1,0,0,1,0,0],"masksToBounds":false,"rotation":0,"scale":1,"position":{"pointX":802.52569580078125,"pointY":481.51541137695312},"width":1608,"sublayerTransform":[1,0,0,0,0,1,0,0,0,0,1,0,0,0,0,1],"contentsRect":{"y":0,"x":0,"width":1,"height":1},"opacity":1,"edgeAntialiasingMask":0,"height":966,"hidden":false,"anchorPoint":{"pointX":0.5000159799756102,"pointY":0.49983032100195718}},"texture":"5E5183275F1F8BA83123FE7F6946803E"}]},{"animations":[{"additive":false,"timeOffset":0,"beginTime":0,"repeatCount":0,"fillMode":"both","duration":1,"autoreverses":false,"animations":[{"repeatCount":0,"removedOnCompletion":true,"from":{"scalar":0.0050000000000000001},"timingFunction":"EaseInEaseOut","additive":false,"timeOffset":0,"autoreverses":false,"property":"zPosition","fillMode":"both","duration":1,"beginTime":0,"to":{"scalar":0.0050000000000000001}}],"removedOnCompletion":false}],"initialState":{"affineTransform":[1,0,0,1,0,0],"masksToBounds":false,"rotation":0,"scale":1,"position":{"pointX":2173.5113830566406,"pointY":300.6461181640625},"width":798.97735595703102,"sublayerTransform":[1,0,0,0,0,1,0,0,0,0,1,0,0,0,0,1],"contentsRect":{"y":0,"x":0,"width":1,"height":1},"opacity":1,"edgeAntialiasingMask":251658240,"height":535.707763671875,"hidden":false,"anchorPoint":{"pointX":0.5,"pointY":0.5}},"layers":[{"animations":[{"additive":false,"timeOffset":0,"beginTime":0,"repeatCount":0,"fillMode":"both","duration":1,"autoreverses":false,"animations":[{"repeatCount":0,"removedOnCompletion":true,"from":{"texture":"CBDD5B23089DF60DE60F591CF37FF822"},"timingFunction":"EaseInEaseOut","additive":false,"timeOffset":0,"autoreverses":false,"property":"contents","fillMode":"both","duration":1,"beginTime":0,"to":{"texture":"CBDD5B23089DF60DE60F591CF37FF822"}},{"additive":false,"timeOffset":0,"beginTime":0,"from":{"scalar":-1.3969952382630173},"repeatCount":0,"fillMode":"both","duration":1,"autoreverses":false,"property":"transform.rotation.z","to":{"scalar":-1.3969952382630173},"removedOnCompletion":true},{"repeatCount":0,"removedOnCompletion":true,"from":{"pointX":0,"pointY":0},"timingFunction":"EaseInEaseOut","additive":false,"timeOffset":0,"autoreverses":false,"property":"transform.translation","fillMode":"both","duration":1,"beginTime":0,"to":{"pointX":-448,"pointY":-84}}],"removedOnCompletion":false}],"layers":[],"texturedRectangle":{"isBackgroundTexture":true,"singleTextureOpacity":1,"textureType":5,"textBaseline":0,"textXHeight":0,"isVerticalText":false},"initialState":{"affineTransform":[0.17292741280544968,-0.98493457138046159,0.98493457138046159,0.17292741280544968,0,0],"masksToBounds":false,"rotation":-1.3969952382630173,"scale":1,"position":{"pointX":399.4886779785154,"pointY":267.85388183593744},"width":802,"sublayerTransform":[1,0,0,0,0,1,0,0,0,0,1,0,0,0,0,1],"contentsRect":{"y":0,"x":0,"width":1,"height":1},"opacity":1,"edgeAntialiasingMask":0,"height":539,"hidden":false,"anchorPoint":{"pointX":0.4993907519409484,"pointY":0.50027109121347391}},"texture":"CBDD5B23089DF60DE60F591CF37FF822"}]},{"animations":[{"additive":false,"timeOffset":0,"beginTime":0,"repeatCount":0,"fillMode":"both","duration":1,"autoreverses":false,"animations":[{"repeatCount":0,"removedOnCompletion":true,"from":{"scalar":0.0060000000000000001},"timingFunction":"EaseInEaseOut","additive":false,"timeOffset":0,"autoreverses":false,"property":"zPosition","fillMode":"both","duration":1,"beginTime":0,"to":{"scalar":0.0060000000000000001}}],"removedOnCompletion":false}],"initialState":{"affineTransform":[1,0,0,1,0,0],"masksToBounds":false,"rotation":0,"scale":1,"position":{"pointX":1383.3723297119141,"pointY":1331.3879547119141},"width":509.25540161132812,"sublayerTransform":[1,0,0,0,0,1,0,0,0,0,1,0,0,0,0,1],"contentsRect":{"y":0,"x":0,"width":1,"height":1},"opacity":1,"edgeAntialiasingMask":251658240,"height":509.25540161132812,"hidden":false,"anchorPoint":{"pointX":0.5,"pointY":0.5}},"layers":[{"animations":[{"additive":false,"timeOffset":0,"beginTime":0,"repeatCount":0,"fillMode":"both","duration":1,"autoreverses":false,"animations":[{"repeatCount":0,"removedOnCompletion":true,"from":{"scalar":1},"timingFunction":"EaseInEaseOut","additive":false,"timeOffset":0,"autoreverses":false,"property":"transform.scale.x","fillMode":"both","duration":1,"beginTime":0,"to":{"scalar":0.99805068226120852}},{"repeatCount":0,"removedOnCompletion":true,"from":{"scalar":1},"timingFunction":"EaseInEaseOut","additive":false,"timeOffset":0,"autoreverses":false,"property":"transform.scale.y","fillMode":"both","duration":1,"beginTime":0,"to":{"scalar":1}},{"repeatCount":0,"removedOnCompletion":true,"from":{"texture":"9BE02F6FC5B80C71FE8949B0FC309186"},"timingFunction":"EaseInEaseOut","additive":false,"timeOffset":0,"autoreverses":false,"property":"contents","fillMode":"both","duration":0.66669999999999996,"beginTime":0.33330000000000004,"to":{"texture":"E373C094B507EF76D2FF3D4FBF71E077"}},{"repeatCount":0,"removedOnCompletion":true,"from":{"pointX":0,"pointY":0},"timingFunction":"EaseInEaseOut","additive":false,"timeOffset":0,"autoreverses":false,"property":"transform.translation","fillMode":"both","duration":1,"beginTime":0,"to":{"pointX":-196.4997511300428,"pointY":-504}}],"removedOnCompletion":false}],"layers":[],"texturedRectangle":{"isBackgroundTexture":true,"singleTextureOpacity":1,"textureType":5,"textBaseline":0,"textXHeight":0,"isVerticalText":false},"initialState":{"affineTransform":[1,0,0,1,0,0],"masksToBounds":false,"rotation":0,"scale":1,"position":{"pointX":254.62770080566406,"pointY":254.62770080566406},"width":513,"sublayerTransform":[1,0,0,0,0,1,0,0,0,0,1,0,0,0,0,1],"contentsRect":{"y":0,"x":0,"width":1,"height":1},"opacity":1,"edgeAntialiasingMask":0,"height":513,"hidden":false,"anchorPoint":{"pointX":0.49975113004271748,"pointY":0.4997815881323861}},"texture":"9BE02F6FC5B80C71FE8949B0FC309186"}]},{"animations":[{"additive":false,"timeOffset":0,"beginTime":0,"repeatCount":0,"fillMode":"both","duration":1,"autoreverses":false,"animations":[{"repeatCount":0,"removedOnCompletion":true,"from":{"scalar":0.0070000000000000001},"timingFunction":"EaseInEaseOut","additive":false,"timeOffset":0,"autoreverses":false,"property":"zPosition","fillMode":"both","duration":1,"beginTime":0,"to":{"scalar":0.0070000000000000001}}],"removedOnCompletion":false}],"initialState":{"affineTransform":[1,0,0,1,0,0],"masksToBounds":false,"rotation":0,"scale":1,"position":{"pointX":440.43731689453125,"pointY":1411.5346069335938},"width":766.8746337890625,"sublayerTransform":[1,0,0,0,0,1,0,0,0,0,1,0,0,0,0,1],"contentsRect":{"y":0,"x":0,"width":1,"height":1},"opacity":1,"edgeAntialiasingMask":251658240,"height":880.4246826171875,"hidden":false,"anchorPoint":{"pointX":0.5,"pointY":0.5}},"layers":[{"animations":[{"additive":false,"timeOffset":0,"beginTime":0,"repeatCount":0,"fillMode":"both","duration":1,"autoreverses":false,"animations":[{"repeatCount":0,"removedOnCompletion":true,"from":{"texture":"78508608182FAB3EE650F9382A01EC41"},"timingFunction":"EaseInEaseOut","additive":false,"timeOffset":0,"autoreverses":false,"property":"contents","fillMode":"both","duration":1,"beginTime":0,"to":{"texture":"78508608182FAB3EE650F9382A01EC41"}},{"repeatCount":0,"removedOnCompletion":true,"from":{"pointX":0,"pointY":0},"timingFunction":"EaseInEaseOut","additive":false,"timeOffset":0,"autoreverses":false,"property":"transform.translation","fillMode":"both","duration":1,"beginTime":0,"to":{"pointX":76,"pointY":-968}}],"removedOnCompletion":false}],"layers":[],"texturedRectangle":{"isBackgroundTexture":true,"singleTextureOpacity":1,"textureType":5,"textBaseline":0,"textXHeight":0,"isVerticalText":false},"initialState":{"affineTransform":[1,0,0,1,0,0],"masksToBounds":false,"rotation":0,"scale":1,"position":{"pointX":383.43731689453125,"pointY":440.21234130859375},"width":769,"sublayerTransform":[1,0,0,0,0,1,0,0,0,0,1,0,0,0,0,1],"contentsRect":{"y":0,"x":0,"width":1,"height":1},"opacity":1,"edgeAntialiasingMask":0,"height":883,"hidden":false,"anchorPoint":{"pointX":0.49991848750914336,"pointY":0.50003919245027606}},"texture":"78508608182FAB3EE650F9382A01EC41"}]},{"animations":[{"additive":false,"timeOffset":0,"beginTime":0,"repeatCount":0,"fillMode":"both","duration":1,"autoreverses":false,"animations":[{"repeatCount":0,"removedOnCompletion":true,"from":{"scalar":0.0080000000000000002},"timingFunction":"EaseInEaseOut","additive":false,"timeOffset":0,"autoreverses":false,"property":"zPosition","fillMode":"both","duration":1,"beginTime":0,"to":{"scalar":0.0080000000000000002}}],"removedOnCompletion":false}],"initialState":{"affineTransform":[1,0,0,1,0,0],"masksToBounds":false,"rotation":0,"scale":1,"position":{"pointX":2044.3170471191406,"pointY":993.87232971191406},"width":558.36602783203125,"sublayerTransform":[1,0,0,0,0,1,0,0,0,0,1,0,0,0,0,1],"contentsRect":{"y":0,"x":0,"width":1,"height":1},"opacity":1,"edgeAntialiasingMask":251658240,"height":509.25540161132812,"hidden":false,"anchorPoint":{"pointX":0.5,"pointY":0.5}},"layers":[{"animations":[{"additive":false,"timeOffset":0,"beginTime":0,"repeatCount":0,"fillMode":"both","duration":1,"autoreverses":false,"animations":[{"repeatCount":0,"removedOnCompletion":true,"from":{"texture":"B1212B6D950D4391052A9C47C6D0A889"},"timingFunction":"EaseInEaseOut","additive":false,"timeOffset":0,"autoreverses":false,"property":"contents","fillMode":"both","duration":1,"beginTime":0,"to":{"texture":"B1212B6D950D4391052A9C47C6D0A889"}},{"repeatCount":0,"removedOnCompletion":true,"from":{"pointX":0,"pointY":0},"timingFunction":"EaseInEaseOut","additive":false,"timeOffset":0,"autoreverses":false,"property":"transform.translation","fillMode":"both","duration":1,"beginTime":0,"to":{"pointX":-406,"pointY":-160}}],"removedOnCompletion":false}],"layers":[],"texturedRectangle":{"isBackgroundTexture":true,"singleTextureOpacity":1,"textureType":5,"textBaseline":0,"textXHeight":0,"isVerticalText":false},"initialState":{"affineTransform":[1,0,0,1,0,0],"masksToBounds":false,"rotation":0,"scale":1,"position":{"pointX":279.18301391601562,"pointY":254.62770080566406},"width":561,"sublayerTransform":[1,0,0,0,0,1,0,0,0,0,1,0,0,0,0,1],"contentsRect":{"y":0,"x":0,"width":1,"height":1},"opacity":1,"edgeAntialiasingMask":0,"height":512,"hidden":false,"anchorPoint":{"pointX":0.49967388078278185,"pointY":0.49975064396858215}},"texture":"B1212B6D950D4391052A9C47C6D0A889"}]},{"animations":[{"additive":false,"timeOffset":0,"beginTime":0,"repeatCount":0,"fillMode":"both","duration":1,"autoreverses":false,"animations":[{"repeatCount":0,"removedOnCompletion":true,"from":{"scalar":0.0090000000000000011},"timingFunction":"EaseInEaseOut","additive":false,"timeOffset":0,"autoreverses":false,"property":"zPosition","fillMode":"both","duration":1,"beginTime":0,"to":{"scalar":0.0090000000000000011}}],"removedOnCompletion":false}],"initialState":{"affineTransform":[1,0,0,1,0,0],"masksToBounds":false,"rotation":0,"scale":1,"position":{"pointX":-260,"pointY":786},"width":433,"sublayerTransform":[1,0,0,0,0,1,0,0,0,0,1,0,0,0,0,1],"contentsRect":{"y":0,"x":0,"width":1,"height":1},"opacity":1,"edgeAntialiasingMask":251658240,"height":577,"hidden":false,"anchorPoint":{"pointX":0.5,"pointY":0.5}},"layers":[{"animations":[{"additive":false,"timeOffset":0,"beginTime":0,"repeatCount":0,"fillMode":"both","duration":1,"autoreverses":false,"animations":[{"repeatCount":0,"removedOnCompletion":true,"from":{"texture":"416F62ED9726381F58EB430DB9989F21"},"timingFunction":"EaseInEaseOut","additive":false,"timeOffset":0,"autoreverses":false,"property":"contents","fillMode":"both","duration":1,"beginTime":0,"to":{"texture":"416F62ED9726381F58EB430DB9989F21"}},{"repeatCount":0,"removedOnCompletion":true,"from":{"pointX":0,"pointY":0},"timingFunction":"EaseInEaseOut","additive":false,"timeOffset":0,"autoreverses":false,"property":"transform.translation","fillMode":"both","duration":1,"beginTime":0,"to":{"pointX":476,"pointY":0}}],"removedOnCompletion":false}],"layers":[],"texturedRectangle":{"isBackgroundTexture":true,"singleTextureOpacity":1,"textureType":5,"textBaseline":0,"textXHeight":0,"isVerticalText":false},"initialState":{"affineTransform":[1,0,0,1,0,0],"masksToBounds":false,"rotation":0,"scale":1,"position":{"pointX":216.5,"pointY":288.5},"width":436,"sublayerTransform":[1,0,0,0,0,1,0,0,0,0,1,0,0,0,0,1],"contentsRect":{"y":0,"x":0,"width":1,"height":1},"opacity":1,"edgeAntialiasingMask":0,"height":580,"hidden":false,"anchorPoint":{"pointX":0.5,"pointY":0.5}},"texture":"416F62ED9726381F58EB430DB9989F21"}]},{"animations":[{"additive":false,"timeOffset":0,"beginTime":0,"repeatCount":0,"fillMode":"both","duration":1,"autoreverses":false,"animations":[{"repeatCount":0,"removedOnCompletion":true,"from":{"scalar":0.01},"timingFunction":"EaseInEaseOut","additive":false,"timeOffset":0,"autoreverses":false,"property":"zPosition","fillMode":"both","duration":1,"beginTime":0,"to":{"scalar":0.01}}],"removedOnCompletion":false}],"initialState":{"affineTransform":[1,0,0,1,0,0],"masksToBounds":false,"rotation":0,"scale":1,"position":{"pointX":616.0513916015625,"pointY":1381.0085754394531},"width":1056.32666015625,"sublayerTransform":[1,0,0,0,0,1,0,0,0,0,1,0,0,0,0,1],"contentsRect":{"y":0,"x":0,"width":1,"height":1},"opacity":1,"edgeAntialiasingMask":251658240,"height":708.25836181640625,"hidden":false,"anchorPoint":{"pointX":0.5,"pointY":0.5}},"layers":[{"animations":[{"additive":false,"timeOffset":0,"beginTime":0,"repeatCount":0,"fillMode":"both","duration":1,"autoreverses":false,"animations":[{"repeatCount":0,"removedOnCompletion":true,"from":{"texture":"ABE537E55E4D3A760C0FDB22C2340556"},"timingFunction":"EaseInEaseOut","additive":false,"timeOffset":0,"autoreverses":false,"property":"contents","fillMode":"both","duration":1,"beginTime":0,"to":{"texture":"ABE537E55E4D3A760C0FDB22C2340556"}},{"repeatCount":0,"removedOnCompletion":true,"from":{"pointX":0,"pointY":0},"timingFunction":"EaseInEaseOut","additive":false,"timeOffset":0,"autoreverses":false,"property":"transform.translation","fillMode":"both","duration":1,"beginTime":0,"to":{"pointX":92,"pointY":-656}}],"removedOnCompletion":false}],"layers":[],"texturedRectangle":{"isBackgroundTexture":true,"singleTextureOpacity":1,"textureType":5,"textBaseline":0,"textXHeight":0,"isVerticalText":false},"initialState":{"affineTransform":[1,0,0,1,0,0],"masksToBounds":false,"rotation":0,"scale":1,"position":{"pointX":528.163330078125,"pointY":354.12918090820312},"width":1060,"sublayerTransform":[1,0,0,0,0,1,0,0,0,0,1,0,0,0,0,1],"contentsRect":{"y":0,"x":0,"width":1,"height":1},"opacity":1,"edgeAntialiasingMask":0,"height":712,"hidden":false,"anchorPoint":{"pointX":0.50004848264298352,"pointY":0.50001204415653533}},"texture":"ABE537E55E4D3A760C0FDB22C2340556"}]},{"animations":[{"additive":false,"timeOffset":0,"beginTime":0,"repeatCount":0,"fillMode":"both","duration":1,"autoreverses":false,"animations":[{"repeatCount":0,"removedOnCompletion":true,"from":{"scalar":0.010999999999999999},"timingFunction":"EaseInEaseOut","additive":false,"timeOffset":0,"autoreverses":false,"property":"zPosition","fillMode":"both","duration":1,"beginTime":0,"to":{"scalar":0.010999999999999999}}],"removedOnCompletion":false}],"initialState":{"affineTransform":[1,0,0,1,0,0],"masksToBounds":false,"rotation":0,"scale":1,"position":{"pointX":350.04957580566406,"pointY":91.490875244140625},"width":297.421875,"sublayerTransform":[1,0,0,0,0,1,0,0,0,0,1,0,0,0,0,1],"contentsRect":{"y":0,"x":0,"width":1,"height":1},"opacity":1,"edgeAntialiasingMask":251658240,"height":72.79656982421875,"hidden":false,"anchorPoint":{"pointX":0.5,"pointY":0.5}},"layers":[{"animations":[{"additive":false,"timeOffset":0,"beginTime":0,"repeatCount":0,"fillMode":"both","duration":1,"autoreverses":false,"animations":[{"repeatCount":0,"removedOnCompletion":true,"from":{"scalar":0},"timingFunction":"EaseInEaseOut","additive":false,"timeOffset":0,"autoreverses":false,"property":"opacity","fillMode":"both","duration":0.33329999999999999,"beginTime":0.66670000000000007,"to":{"scalar":1}},{"additive":false,"timeOffset":0,"beginTime":0.66670000000000007,"from":{"scalar":false},"repeatCount":0,"fillMode":"forwards","duration":0.33329999999999993,"autoreverses":false,"property":"hidden","to":{"scalar":false},"removedOnCompletion":true}],"removedOnCompletion":false}],"layers":[],"texturedRectangle":{"singleTextureOpacity":1,"textXHeight":0.5157470703125,"textBaseline":0.865576426188151,"isBackgroundTexture":true,"isVerticalText":false,"textColor":[0.97254902124404907,0.97254902124404907,0.94901961088180542,1],"textureType":6},"initialState":{"affineTransform":[1,0,0,1,0,0],"masksToBounds":false,"rotation":0,"scale":1,"position":{"pointX":148.7109375,"pointY":36.398284912109375},"width":98,"sublayerTransform":[1,0,0,0,0,1,0,0,0,0,1,0,0,0,0,1],"contentsRect":{"y":0,"x":0,"width":1,"height":1},"opacity":1,"edgeAntialiasingMask":0,"height":48,"hidden":true,"anchorPoint":{"pointX":0.50050587556800064,"pointY":0.36439323425292969}},"texture":"2AF5D14B5C73FB4641568DEFE2E0953C"}]},{"animations":[{"additive":false,"timeOffset":0,"beginTime":0,"repeatCount":0,"fillMode":"both","duration":1,"autoreverses":false,"animations":[{"repeatCount":0,"removedOnCompletion":true,"from":{"scalar":0.012},"timingFunction":"EaseInEaseOut","additive":false,"timeOffset":0,"autoreverses":false,"property":"zPosition","fillMode":"both","duration":1,"beginTime":0,"to":{"scalar":0.012}}],"removedOnCompletion":false}],"initialState":{"affineTransform":[1,0,0,1,0,0],"masksToBounds":false,"rotation":0,"scale":1,"position":{"pointX":752.7578125,"pointY":122.24868774414061},"width":381.515625,"sublayerTransform":[1,0,0,0,0,1,0,0,0,0,1,0,0,0,0,1],"contentsRect":{"y":0,"x":0,"width":1,"height":1},"opacity":1,"edgeAntialiasingMask":251658240,"height":102.31219482421878,"hidden":false,"anchorPoint":{"pointX":0.5,"pointY":0.5}},"layers":[{"animations":[{"additive":false,"timeOffset":0,"beginTime":0,"repeatCount":0,"fillMode":"both","duration":1,"autoreverses":false,"animations":[{"repeatCount":0,"removedOnCompletion":true,"from":{"scalar":0},"timingFunction":"EaseInEaseOut","additive":false,"timeOffset":0,"autoreverses":false,"property":"opacity","fillMode":"both","duration":0.33329999999999999,"beginTime":0.66670000000000007,"to":{"scalar":1}},{"additive":false,"timeOffset":0,"beginTime":0.66670000000000007,"from":{"scalar":false},"repeatCount":0,"fillMode":"forwards","duration":0.33329999999999993,"autoreverses":false,"property":"hidden","to":{"scalar":false},"removedOnCompletion":true}],"removedOnCompletion":false}],"layers":[],"texturedRectangle":{"singleTextureOpacity":1,"textXHeight":0.5802154541015625,"textBaseline":0.86512184143066406,"isBackgroundTexture":true,"isVerticalText":false,"textColor":[0.97254902124404907,0.97254902124404907,0.94901961088180542,1],"textureType":6},"initialState":{"affineTransform":[1,0,0,1,0,0],"masksToBounds":false,"rotation":0,"scale":1,"position":{"pointX":190.7578125,"pointY":51.156097412109403},"width":294,"sublayerTransform":[1,0,0,0,0,1,0,0,0,0,1,0,0,0,0,1],"contentsRect":{"y":0,"x":0,"width":1,"height":1},"opacity":1,"edgeAntialiasingMask":0,"height":32,"hidden":true,"anchorPoint":{"pointX":0.4991762329931973,"pointY":-0.39847850799560547}},"texture":"9303FE48D610EF7CDAFEA4BEE56058C4"}]},{"animations":[{"additive":false,"timeOffset":0,"beginTime":0,"repeatCount":0,"fillMode":"both","duration":1,"autoreverses":false,"animations":[{"repeatCount":0,"removedOnCompletion":true,"from":{"scalar":0.013000000000000001},"timingFunction":"EaseInEaseOut","additive":false,"timeOffset":0,"autoreverses":false,"property":"zPosition","fillMode":"both","duration":1,"beginTime":0,"to":{"scalar":0.013000000000000001}}],"removedOnCompletion":false}],"initialState":{"affineTransform":[1,0,0,1,0,0],"masksToBounds":false,"rotation":0,"scale":1,"position":{"pointX":752.7578125,"pointY":122.24868774414061},"width":381.515625,"sublayerTransform":[1,0,0,0,0,1,0,0,0,0,1,0,0,0,0,1],"contentsRect":{"y":0,"x":0,"width":1,"height":1},"opacity":1,"edgeAntialiasingMask":251658240,"height":102.31219482421878,"hidden":false,"anchorPoint":{"pointX":0.5,"pointY":0.5}},"layers":[{"animations":[{"additive":false,"timeOffset":0,"beginTime":0,"repeatCount":0,"fillMode":"both","duration":1,"autoreverses":false,"animations":[{"repeatCount":0,"removedOnCompletion":true,"from":{"scalar":0},"timingFunction":"EaseInEaseOut","additive":false,"timeOffset":0,"autoreverses":false,"property":"opacity","fillMode":"both","duration":0.33329999999999999,"beginTime":0.66670000000000007,"to":{"scalar":1}},{"additive":false,"timeOffset":0,"beginTime":0.66670000000000007,"from":{"scalar":false},"repeatCount":0,"fillMode":"forwards","duration":0.33329999999999993,"autoreverses":false,"property":"hidden","to":{"scalar":false},"removedOnCompletion":true}],"removedOnCompletion":false}],"layers":[],"texturedRectangle":{"singleTextureOpacity":1,"textXHeight":0.50180796030405406,"textBaseline":0.85632159258868246,"isBackgroundTexture":true,"isVerticalText":false,"textColor":[0.97254902124404907,0.97254902124404907,0.94901961088180542,1],"textureType":6},"initialState":{"affineTransform":[1,0,0,1,0,0],"masksToBounds":false,"rotation":0,"scale":1,"position":{"pointX":190.7578125,"pointY":51.156097412109403},"width":374,"sublayerTransform":[1,0,0,0,0,1,0,0,0,0,1,0,0,0,0,1],"contentsRect":{"y":0,"x":0,"width":1,"height":1},"opacity":1,"edgeAntialiasingMask":0,"height":37,"hidden":true,"anchorPoint":{"pointX":0.49935243983957217,"pointY":1.0337483174092061}},"texture":"27B373701DB4D31FC4D592353D6E6AAC"}]},{"animations":[{"additive":false,"timeOffset":0,"beginTime":0,"repeatCount":0,"fillMode":"both","duration":1,"autoreverses":false,"animations":[{"repeatCount":0,"removedOnCompletion":true,"from":{"scalar":0.014},"timingFunction":"EaseInEaseOut","additive":false,"timeOffset":0,"autoreverses":false,"property":"zPosition","fillMode":"both","duration":1,"beginTime":0,"to":{"scalar":0.014}}],"removedOnCompletion":false}],"initialState":{"affineTransform":[1,0,0,1,0,0],"masksToBounds":false,"rotation":0,"scale":1,"position":{"pointX":812.7109375,"pointY":345.53460693359375},"width":297.421875,"sublayerTransform":[1,0,0,0,0,1,0,0,0,0,1,0,0,0,0,1],"contentsRect":{"y":0,"x":0,"width":1,"height":1},"opacity":1,"edgeAntialiasingMask":251658240,"height":72.79656982421875,"hidden":false,"anchorPoint":{"pointX":0.5,"pointY":0.5}},"layers":[{"animations":[{"additive":false,"timeOffset":0,"beginTime":0,"repeatCount":0,"fillMode":"both","duration":1,"autoreverses":false,"animations":[{"repeatCount":0,"removedOnCompletion":true,"from":{"scalar":0},"timingFunction":"EaseInEaseOut","additive":false,"timeOffset":0,"autoreverses":false,"property":"opacity","fillMode":"both","duration":0.33329999999999999,"beginTime":0.66670000000000007,"to":{"scalar":1}},{"additive":false,"timeOffset":0,"beginTime":0.66670000000000007,"from":{"scalar":false},"repeatCount":0,"fillMode":"forwards","duration":0.33329999999999993,"autoreverses":false,"property":"hidden","to":{"scalar":false},"removedOnCompletion":true}],"removedOnCompletion":false}],"layers":[],"texturedRectangle":{"singleTextureOpacity":1,"textXHeight":0.52672041223404253,"textBaseline":0.86364681162732715,"isBackgroundTexture":true,"isVerticalText":false,"textColor":[0.97254902124404907,0.97254902124404907,0.94901961088180542,1],"textureType":6},"initialState":{"affineTransform":[1,0,0,1,0,0],"masksToBounds":false,"rotation":0,"scale":1,"position":{"pointX":148.7109375,"pointY":36.398284912109375},"width":148,"sublayerTransform":[1,0,0,0,0,1,0,0,0,0,1,0,0,0,0,1],"contentsRect":{"y":0,"x":0,"width":1,"height":1},"opacity":1,"edgeAntialiasingMask":0,"height":47,"hidden":true,"anchorPoint":{"pointX":0.498046875,"pointY":0.35180014752327127}},"texture":"F2DAB0D8CC060BFE0FF91E035EADADBA"}]},{"animations":[{"additive":false,"timeOffset":0,"beginTime":0,"repeatCount":0,"fillMode":"both","duration":1,"autoreverses":false,"animations":[{"repeatCount":0,"removedOnCompletion":true,"from":{"scalar":0.014999999999999999},"timingFunction":"EaseInEaseOut","additive":false,"timeOffset":0,"autoreverses":false,"property":"zPosition","fillMode":"both","duration":1,"beginTime":0,"to":{"scalar":0.014999999999999999}}],"removedOnCompletion":false}],"initialState":{"affineTransform":[1,0,0,1,0,0],"masksToBounds":false,"rotation":0,"scale":1,"position":{"pointX":470.2109375,"pointY":695.88351440429688},"width":216.421875,"sublayerTransform":[1,0,0,0,0,1,0,0,0,0,1,0,0,0,0,1],"contentsRect":{"y":0,"x":0,"width":1,"height":1},"opacity":1,"edgeAntialiasingMask":251658240,"height":62.546569824218864,"hidden":false,"anchorPoint":{"pointX":0.5,"pointY":0.5}},"layers":[{"animations":[{"additive":false,"timeOffset":0,"beginTime":0,"repeatCount":0,"fillMode":"both","duration":1,"autoreverses":false,"animations":[{"repeatCount":0,"removedOnCompletion":true,"from":{"scalar":0},"timingFunction":"EaseInEaseOut","additive":false,"timeOffset":0,"autoreverses":false,"property":"opacity","fillMode":"both","duration":0.33329999999999999,"beginTime":0.66670000000000007,"to":{"scalar":1}},{"additive":false,"timeOffset":0,"beginTime":0.66670000000000007,"from":{"scalar":false},"repeatCount":0,"fillMode":"forwards","duration":0.33329999999999993,"autoreverses":false,"property":"hidden","to":{"scalar":false},"removedOnCompletion":true}],"removedOnCompletion":false}],"layers":[],"texturedRectangle":{"singleTextureOpacity":1,"textXHeight":0.50926339285714284,"textBaseline":0.87022530691964284,"isBackgroundTexture":true,"isVerticalText":false,"textColor":[0.97254902124404907,0.97254902124404907,0.94901961088180542,1],"textureType":6},"initialState":{"affineTransform":[1,0,0,1,0,0],"masksToBounds":false,"rotation":0,"scale":1,"position":{"pointX":108.2109375,"pointY":31.273284912109489},"width":207,"sublayerTransform":[1,0,0,0,0,1,0,0,0,0,1,0,0,0,0,1],"contentsRect":{"y":0,"x":0,"width":1,"height":1},"opacity":1,"edgeAntialiasingMask":0,"height":35,"hidden":true,"anchorPoint":{"pointX":0.49860356280193235,"pointY":0.36810041155133927}},"texture":"E7B509513C785FFB14F4900734FC5E6C"}]},{"animations":[{"additive":false,"timeOffset":0,"beginTime":0,"repeatCount":0,"fillMode":"both","duration":1,"autoreverses":false,"animations":[{"repeatCount":0,"removedOnCompletion":true,"from":{"scalar":0.016},"timingFunction":"EaseInEaseOut","additive":false,"timeOffset":0,"autoreverses":false,"property":"zPosition","fillMode":"both","duration":1,"beginTime":0,"to":{"scalar":0.016}}],"removedOnCompletion":false}],"initialState":{"affineTransform":[1,0,0,1,0,0],"masksToBounds":false,"rotation":0,"scale":1,"position":{"pointX":1409.372314453125,"pointY":520.6461181640625},"width":297.421875,"sublayerTransform":[1,0,0,0,0,1,0,0,0,0,1,0,0,0,0,1],"contentsRect":{"y":0,"x":0,"width":1,"height":1},"opacity":1,"edgeAntialiasingMask":251658240,"height":72.79656982421875,"hidden":false,"anchorPoint":{"pointX":0.5,"pointY":0.5}},"layers":[{"animations":[{"additive":false,"timeOffset":0,"beginTime":0,"repeatCount":0,"fillMode":"both","duration":1,"autoreverses":false,"animations":[{"repeatCount":0,"removedOnCompletion":true,"from":{"scalar":0},"timingFunction":"EaseInEaseOut","additive":false,"timeOffset":0,"autoreverses":false,"property":"opacity","fillMode":"both","duration":0.33329999999999999,"beginTime":0.66670000000000007,"to":{"scalar":1}},{"additive":false,"timeOffset":0,"beginTime":0.66670000000000007,"from":{"scalar":false},"repeatCount":0,"fillMode":"forwards","duration":0.33329999999999993,"autoreverses":false,"property":"hidden","to":{"scalar":false},"removedOnCompletion":true}],"removedOnCompletion":false}],"layers":[],"texturedRectangle":{"singleTextureOpacity":1,"textXHeight":0.5157470703125,"textBaseline":0.86881065368652344,"isBackgroundTexture":true,"isVerticalText":false,"textColor":[0.97254902124404907,0.97254902124404907,0.94901961088180542,1],"textureType":6},"initialState":{"affineTransform":[1,0,0,1,0,0],"masksToBounds":false,"rotation":0,"scale":1,"position":{"pointX":148.7109375,"pointY":36.398284912109375},"width":237,"sublayerTransform":[1,0,0,0,0,1,0,0,0,0,1,0,0,0,0,1],"contentsRect":{"y":0,"x":0,"width":1,"height":1},"opacity":1,"edgeAntialiasingMask":0,"height":48,"hidden":true,"anchorPoint":{"pointX":0.49524183313554854,"pointY":0.36762746175130206}},"texture":"1D50D4427BE7767B6298F1E7272B7517"}]},{"animations":[{"additive":false,"timeOffset":0,"beginTime":0,"repeatCount":0,"fillMode":"both","duration":1,"autoreverses":false,"animations":[{"repeatCount":0,"removedOnCompletion":true,"from":{"scalar":0.017000000000000001},"timingFunction":"EaseInEaseOut","additive":false,"timeOffset":0,"autoreverses":false,"property":"zPosition","fillMode":"both","duration":1,"beginTime":0,"to":{"scalar":0.017000000000000001}}],"removedOnCompletion":false}],"initialState":{"affineTransform":[1,0,0,1,0,0],"masksToBounds":false,"rotation":0,"scale":1,"position":{"pointX":1232.89453125,"pointY":186.015625},"width":350.9296875,"sublayerTransform":[1,0,0,0,0,1,0,0,0,0,1,0,0,0,0,1],"contentsRect":{"y":0,"x":0,"width":1,"height":1},"opacity":1,"edgeAntialiasingMask":251658240,"height":119.42156982421875,"hidden":false,"anchorPoint":{"pointX":0.5,"pointY":0.5}},"layers":[{"animations":[{"additive":false,"timeOffset":0,"beginTime":0,"repeatCount":0,"fillMode":"both","duration":1,"autoreverses":false,"animations":[{"repeatCount":0,"removedOnCompletion":true,"from":{"scalar":0},"timingFunction":"EaseInEaseOut","additive":false,"timeOffset":0,"autoreverses":false,"property":"opacity","fillMode":"both","duration":0.33329999999999999,"beginTime":0.66670000000000007,"to":{"scalar":1}},{"additive":false,"timeOffset":0,"beginTime":0.66670000000000007,"from":{"scalar":false},"repeatCount":0,"fillMode":"forwards","duration":0.33329999999999993,"autoreverses":false,"property":"hidden","to":{"scalar":false},"removedOnCompletion":true}],"removedOnCompletion":false}],"layers":[],"texturedRectangle":{"singleTextureOpacity":1,"textXHeight":0.50146484375,"textBaseline":0.86036799504206729,"isBackgroundTexture":true,"isVerticalText":false,"textColor":[0.97254902124404907,0.97254902124404907,0.94901961088180542,1],"textureType":6},"initialState":{"affineTransform":[1,0,0,1,0,0],"masksToBounds":false,"rotation":0,"scale":1,"position":{"pointX":175.46484375,"pointY":59.710784912109375},"width":237,"sublayerTransform":[1,0,0,0,0,1,0,0,0,0,1,0,0,0,0,1],"contentsRect":{"y":0,"x":0,"width":1,"height":1},"opacity":1,"edgeAntialiasingMask":0,"height":39,"hidden":true,"anchorPoint":{"pointX":0.50166468881856541,"pointY":1.0260416666666667}},"texture":"E1179C3FB2577AB4FB025FB9EB4E6E83"}]},{"animations":[{"additive":false,"timeOffset":0,"beginTime":0,"repeatCount":0,"fillMode":"both","duration":1,"autoreverses":false,"animations":[{"repeatCount":0,"removedOnCompletion":true,"from":{"scalar":0.018000000000000002},"timingFunction":"EaseInEaseOut","additive":false,"timeOffset":0,"autoreverses":false,"property":"zPosition","fillMode":"both","duration":1,"beginTime":0,"to":{"scalar":0.018000000000000002}}],"removedOnCompletion":false}],"initialState":{"affineTransform":[1,0,0,1,0,0],"masksToBounds":false,"rotation":0,"scale":1,"position":{"pointX":1232.89453125,"pointY":186.015625},"width":350.9296875,"sublayerTransform":[1,0,0,0,0,1,0,0,0,0,1,0,0,0,0,1],"contentsRect":{"y":0,"x":0,"width":1,"height":1},"opacity":1,"edgeAntialiasingMask":251658240,"height":119.42156982421875,"hidden":false,"anchorPoint":{"pointX":0.5,"pointY":0.5}},"layers":[{"animations":[{"additive":false,"timeOffset":0,"beginTime":0,"repeatCount":0,"fillMode":"both","duration":1,"autoreverses":false,"animations":[{"repeatCount":0,"removedOnCompletion":true,"from":{"scalar":0},"timingFunction":"EaseInEaseOut","additive":false,"timeOffset":0,"autoreverses":false,"property":"opacity","fillMode":"both","duration":0.33329999999999999,"beginTime":0.66670000000000007,"to":{"scalar":1}},{"additive":false,"timeOffset":0,"beginTime":0.66670000000000007,"from":{"scalar":false},"repeatCount":0,"fillMode":"forwards","duration":0.33329999999999993,"autoreverses":false,"property":"hidden","to":{"scalar":false},"removedOnCompletion":true}],"removedOnCompletion":false}],"layers":[],"texturedRectangle":{"singleTextureOpacity":1,"textXHeight":0.57520967371323528,"textBaseline":0.86924564137178306,"isBackgroundTexture":true,"isVerticalText":false,"textColor":[0.97254902124404907,0.97254902124404907,0.94901961088180542,1],"textureType":6},"initialState":{"affineTransform":[1,0,0,1,0,0],"masksToBounds":false,"rotation":0,"scale":1,"position":{"pointX":175.46484375,"pointY":59.710784912109375},"width":346,"sublayerTransform":[1,0,0,0,0,1,0,0,0,0,1,0,0,0,0,1],"contentsRect":{"y":0,"x":0,"width":1,"height":1},"opacity":1,"edgeAntialiasingMask":0,"height":34,"hidden":true,"anchorPoint":{"pointX":0.49969517702312138,"pointY":-0.41130514705882354}},"texture":"0FB273F8C0876C3FC3D36949432391AB"}]},{"animations":[{"additive":false,"timeOffset":0,"beginTime":0,"repeatCount":0,"fillMode":"both","duration":1,"autoreverses":false,"animations":[{"repeatCount":0,"removedOnCompletion":true,"from":{"scalar":0.019},"timingFunction":"EaseInEaseOut","additive":false,"timeOffset":0,"autoreverses":false,"property":"zPosition","fillMode":"both","duration":1,"beginTime":0,"to":{"scalar":0.019}}],"removedOnCompletion":false}],"initialState":{"affineTransform":[1,0,0,1,0,0],"masksToBounds":false,"rotation":0,"scale":1,"position":{"pointX":1468.7109375,"pointY":863.78622436523438},"width":297.421875,"sublayerTransform":[1,0,0,0,0,1,0,0,0,0,1,0,0,0,0,1],"contentsRect":{"y":0,"x":0,"width":1,"height":1},"opacity":1,"edgeAntialiasingMask":251658240,"height":72.79656982421875,"hidden":false,"anchorPoint":{"pointX":0.5,"pointY":0.5}},"layers":[{"animations":[{"additive":false,"timeOffset":0,"beginTime":0,"repeatCount":0,"fillMode":"both","duration":1,"autoreverses":false,"animations":[{"repeatCount":0,"removedOnCompletion":true,"from":{"scalar":0},"timingFunction":"EaseInEaseOut","additive":false,"timeOffset":0,"autoreverses":false,"property":"opacity","fillMode":"both","duration":0.33329999999999999,"beginTime":0.66670000000000007,"to":{"scalar":1}},{"additive":false,"timeOffset":0,"beginTime":0.66670000000000007,"from":{"scalar":false},"repeatCount":0,"fillMode":"forwards","duration":0.33329999999999993,"autoreverses":false,"property":"hidden","to":{"scalar":false},"removedOnCompletion":true}],"removedOnCompletion":false}],"layers":[],"texturedRectangle":{"singleTextureOpacity":1,"textXHeight":0.52672041223404253,"textBaseline":0.86900037400265961,"isBackgroundTexture":true,"isVerticalText":false,"textColor":[0.97254902124404907,0.97254902124404907,0.94901961088180542,1],"textureType":6},"initialState":{"affineTransform":[1,0,0,1,0,0],"masksToBounds":false,"rotation":0,"scale":1,"position":{"pointX":148.7109375,"pointY":36.398284912109375},"width":146,"sublayerTransform":[1,0,0,0,0,1,0,0,0,0,1,0,0,0,0,1],"contentsRect":{"y":0,"x":0,"width":1,"height":1},"opacity":1,"edgeAntialiasingMask":0,"height":47,"hidden":true,"anchorPoint":{"pointX":0.49117080479452052,"pointY":0.35715370989860373}},"texture":"CC4B95A4BE772319D0FA1F96092A5C80"}]},{"animations":[{"additive":false,"timeOffset":0,"beginTime":0,"repeatCount":0,"fillMode":"both","duration":1,"autoreverses":false,"animations":[{"repeatCount":0,"removedOnCompletion":true,"from":{"scalar":0.02},"timingFunction":"EaseInEaseOut","additive":false,"timeOffset":0,"autoreverses":false,"property":"zPosition","fillMode":"both","duration":1,"beginTime":0,"to":{"scalar":0.02}}],"removedOnCompletion":false}],"initialState":{"affineTransform":[1,0,0,1,0,0],"masksToBounds":false,"rotation":0,"scale":1,"position":{"pointX":1560.7109375,"pointY":331.53460693359375},"width":297.421875,"sublayerTransform":[1,0,0,0,0,1,0,0,0,0,1,0,0,0,0,1],"contentsRect":{"y":0,"x":0,"width":1,"height":1},"opacity":1,"edgeAntialiasingMask":251658240,"height":72.79656982421875,"hidden":false,"anchorPoint":{"pointX":0.5,"pointY":0.5}},"layers":[{"animations":[{"additive":false,"timeOffset":0,"beginTime":0,"repeatCount":0,"fillMode":"both","duration":1,"autoreverses":false,"animations":[{"repeatCount":0,"removedOnCompletion":true,"from":{"scalar":0},"timingFunction":"EaseInEaseOut","additive":false,"timeOffset":0,"autoreverses":false,"property":"opacity","fillMode":"both","duration":0.33329999999999999,"beginTime":0.66670000000000007,"to":{"scalar":1}},{"additive":false,"timeOffset":0,"beginTime":0.66670000000000007,"from":{"scalar":false},"repeatCount":0,"fillMode":"forwards","duration":0.33329999999999993,"autoreverses":false,"property":"hidden","to":{"scalar":false},"removedOnCompletion":true}],"removedOnCompletion":false}],"layers":[],"texturedRectangle":{"singleTextureOpacity":1,"textXHeight":0.5157470703125,"textBaseline":0.86648750305175781,"isBackgroundTexture":true,"isVerticalText":false,"textColor":[0.97254902124404907,0.97254902124404907,0.94901961088180542,1],"textureType":6},"initialState":{"affineTransform":[1,0,0,1,0,0],"masksToBounds":false,"rotation":0,"scale":1,"position":{"pointX":148.7109375,"pointY":36.398284912109375},"width":236,"sublayerTransform":[1,0,0,0,0,1,0,0,0,0,1,0,0,0,0,1],"contentsRect":{"y":0,"x":0,"width":1,"height":1},"opacity":1,"edgeAntialiasingMask":0,"height":48,"hidden":true,"anchorPoint":{"pointX":0.49877515889830509,"pointY":0.36530431111653644}},"texture":"D1963322FF6D6EB9958D88884468DCB7"}]}]},"effects":[],"duration":1,"type":"transition","attributes":{"direction":0},"name":"apple:magic-move-implied-motion-path","objectID":"0"}],"automaticPlay":false,"hyperlinks":[],"accessibility":[{"text":"Steve_Jobs_flickr_8010717_N02_6216457030_segagman-removebg-preview.png","targetRectangle":{"y":739.24462890625,"x":1765.134033203125,"width":558.36602783203125,"height":509.25540161132812}},{"text":"article-601d0119d549b-removebg-preview.png","targetRectangle":{"y":-139.1433704478394,"x":1840.6102912300748,"width":665.80218365313203,"height":879.57897722380369}},{"text":"額...","targetRectangle":{"y":608.4298095703125,"x":208.55859375,"width":101.02399988108874,"height":80.40000319480896}},{"text":"images-removebg-preview.png","targetRectangle":{"y":1076.76025390625,"x":1128.74462890625,"width":509.25540161132812,"height":509.25540161132812}},{"text":"C1428466668760-removebg-preview.png","targetRectangle":{"y":-29.595162683956119,"x":-798.78100386235371,"width":965.56194668955106,"height":810.25953923509974}},{"text":"3500-removebg-preview.png","targetRectangle":{"y":817.3206787109375,"x":305.5,"width":1605.0513916015625,"height":963.03082275390625}},{"text":"C1453949543828-removebg-preview.png","targetRectangle":{"y":1026.87939453125,"x":87.8880615234375,"width":1056.32666015625,"height":708.25836181640625}},{"text":"Walt_Disney_1946__cropped2_-removebg-preview.png","targetRectangle":{"y":497.5,"x":-476.5,"width":433,"height":577}},{"text":"想拿學歷以後找好工作。","targetRectangle":{"y":394.5545654296875,"x":206.24609375,"width":1276.2421866506338,"height":151}},{"text":"images-removebg-preview(1).png","targetRectangle":{"y":971.322265625,"x":57,"width":766.8746337890625,"height":880.4246826171875}}],"baseLayer":{"animations":[],"initialState":{"affineTransform":[1,0,0,1,0,0],"masksToBounds":false,"rotation":0,"scale":1,"position":{"pointX":960,"pointY":540},"width":1920,"sublayerTransform":[1,0,0,0,0,1,0,0,0,0,1,0,0,0,0,1],"contentsRect":{"y":0,"x":0,"width":1,"height":1},"opacity":1,"edgeAntialiasingMask":251658240,"height":1080,"hidden":false,"anchorPoint":{"pointX":0.5,"pointY":0.5}},"objectID":"0","layers":[{"animations":[],"initialState":{"affineTransform":[1,0,0,1,0,0],"masksToBounds":false,"rotation":0,"scale":1,"position":{"pointX":960,"pointY":540},"width":1920,"sublayerTransform":[1,0,0,0,0,1,0,0,0,0,1,-0.00035007912466775983,0,0,0,1],"contentsRect":{"y":0,"x":0,"width":1,"height":1},"opacity":1,"edgeAntialiasingMask":251658240,"height":1080,"hidden":false,"anchorPoint":{"pointX":0.5,"pointY":0.5}},"layers":[{"animations":[],"initialState":{"affineTransform":[1,0,0,1,0,0],"masksToBounds":false,"rotation":0,"scale":1,"position":{"pointX":960,"pointY":540},"width":1920,"sublayerTransform":[1,0,0,0,0,1,0,0,0,0,1,0,0,0,0,1],"contentsRect":{"y":0,"x":0,"width":1,"height":1},"opacity":1,"edgeAntialiasingMask":251658240,"height":1080,"hidden":false,"anchorPoint":{"pointX":0.5,"pointY":0.5}},"layers":[{"animations":[],"layers":[],"texturedRectangle":{"isBackgroundTexture":true,"singleTextureOpacity":1,"textureType":1,"textBaseline":0,"textXHeight":0,"isVerticalText":false},"initialState":{"affineTransform":[1,0,0,1,0,0],"masksToBounds":false,"rotation":0,"scale":1,"position":{"pointX":960,"pointY":540},"width":1920,"sublayerTransform":[1,0,0,0,0,1,0,0,0,0,1,0,0,0,0,1],"contentsRect":{"y":0,"x":0,"width":1,"height":1},"opacity":1,"edgeAntialiasingMask":0,"height":1080,"hidden":false,"anchorPoint":{"pointX":0.5,"pointY":0.5}},"texture":"371FE67501357F3E8AB21EABAD9AF0C5"}]}]},{"animations":[],"initialState":{"affineTransform":[1,0,0,1,0,0],"masksToBounds":false,"rotation":0,"scale":1,"position":{"pointX":941.3046875,"pointY":469.5858154296875},"width":1478.1171875,"sublayerTransform":[1,0,0,0,0,1,0,0,0,0,1,0,0,0,0,1],"contentsRect":{"y":0,"x":0,"width":1,"height":1},"opacity":1,"edgeAntialiasingMask":251658240,"height":182.06250000000006,"hidden":false,"anchorPoint":{"pointX":0.5,"pointY":0.5}},"layers":[{"animations":[],"layers":[],"texturedRectangle":{"singleTextureOpacity":1,"textXHeight":0.52578816371681414,"textBaseline":0.88536949495298678,"isBackgroundTexture":true,"isVerticalText":false,"textColor":[1,0.47450980544090271,0.7764706015586853,1],"textureType":6},"initialState":{"affineTransform":[1,0,0,1,0,0],"masksToBounds":false,"rotation":0,"scale":1,"position":{"pointX":739.05859375,"pointY":91.031250000000057},"width":1252,"sublayerTransform":[1,0,0,0,0,1,0,0,0,0,1,0,0,0,0,1],"contentsRect":{"y":0,"x":0,"width":1,"height":1},"opacity":1,"edgeAntialiasingMask":0,"height":113,"hidden":false,"anchorPoint":{"pointX":0.58570661940894564,"pointY":0.39456473831581856}},"texture":"AA856C534C8DDB31360A067749ADAA19"}]},{"animations":[],"initialState":{"affineTransform":[1,0,0,1,0,0],"masksToBounds":false,"rotation":0,"scale":1,"position":{"pointX":943.6171875,"pointY":688.96887207031239},"width":1478.1171875,"sublayerTransform":[1,0,0,0,0,1,0,0,0,0,1,0,0,0,0,1],"contentsRect":{"y":0,"x":0,"width":1,"height":1},"opacity":1,"edgeAntialiasingMask":251658240,"height":169.07812500000023,"hidden":false,"anchorPoint":{"pointX":0.5,"pointY":0.5}},"layers":[{"animations":[],"layers":[],"texturedRectangle":{"singleTextureOpacity":1,"textXHeight":0.55287272727272729,"textBaseline":0.88563265366987753,"isBackgroundTexture":true,"isVerticalText":false,"textColor":[0.97254902124404907,0.97254902124404907,0.94901961088180542,1],"textureType":6},"initialState":{"affineTransform":[1,0,0,1,0,0],"masksToBounds":false,"rotation":0,"scale":1,"position":{"pointX":739.05859375,"pointY":84.539062500000227},"width":99,"sublayerTransform":[1,0,0,0,0,1,0,0,0,0,1,0,0,0,0,1],"contentsRect":{"y":0,"x":0,"width":1,"height":1},"opacity":1,"edgeAntialiasingMask":0,"height":55,"hidden":false,"anchorPoint":{"pointX":7.430476641414141,"pointY":1.2539794921875}},"texture":"5455C0F64006A887F0D9A459FADD9818"}]},{"animations":[],"initialState":{"affineTransform":[1,0,0,1,0,0],"masksToBounds":false,"rotation":0,"scale":1,"position":{"pointX":-316.00003051757812,"pointY":375.53460693359375},"width":822.25921630859375,"sublayerTransform":[1,0,0,0,0,1,0,0,0,0,1,0,0,0,0,1],"contentsRect":{"y":0,"x":0,"width":1,"height":1},"opacity":1,"edgeAntialiasingMask":251658240,"height":551.31805419921875,"hidden":false,"anchorPoint":{"pointX":0.5,"pointY":0.5}},"layers":[{"animations":[],"layers":[],"texturedRectangle":{"isBackgroundTexture":true,"singleTextureOpacity":1,"textureType":5,"textBaseline":0,"textXHeight":0,"isVerticalText":false},"initialState":{"affineTransform":[0.93302016012684175,-0.35982409702086737,0.35982409702086737,0.93302016012684175,0,0],"masksToBounds":false,"rotation":-0.3680793558434321,"scale":1,"position":{"pointX":411.12960815429682,"pointY":275.65902709960938},"width":826,"sublayerTransform":[1,0,0,0,0,1,0,0,0,0,1,0,0,0,0,1],"contentsRect":{"y":0,"x":0,"width":1,"height":1},"opacity":1,"edgeAntialiasingMask":0,"height":555,"hidden":false,"anchorPoint":{"pointX":0.49999996305377942,"pointY":0.50006235483530403}},"texture":"E9209884329EC7E772D9A62D0141CADC"}]},{"animations":[],"initialState":{"affineTransform":[1,0,0,1,0,0],"masksToBounds":false,"rotation":0,"scale":1,"position":{"pointX":1108.0256958007812,"pointY":1298.8360900878906},"width":1605.0513916015625,"sublayerTransform":[1,0,0,0,0,1,0,0,0,0,1,0,0,0,0,1],"contentsRect":{"y":0,"x":0,"width":1,"height":1},"opacity":1,"edgeAntialiasingMask":251658240,"height":963.03082275390625,"hidden":false,"anchorPoint":{"pointX":0.5,"pointY":0.5}},"layers":[{"animations":[],"layers":[],"texturedRectangle":{"isBackgroundTexture":true,"singleTextureOpacity":1,"textureType":5,"textBaseline":0,"textXHeight":0,"isVerticalText":false},"initialState":{"affineTransform":[1,0,0,1,0,0],"masksToBounds":false,"rotation":0,"scale":1,"position":{"pointX":802.52569580078125,"pointY":481.51541137695312},"width":1608,"sublayerTransform":[1,0,0,0,0,1,0,0,0,0,1,0,0,0,0,1],"contentsRect":{"y":0,"x":0,"width":1,"height":1},"opacity":1,"edgeAntialiasingMask":0,"height":966,"hidden":false,"anchorPoint":{"pointX":0.5000159799756102,"pointY":0.49983032100195718}},"texture":"5E5183275F1F8BA83123FE7F6946803E"}]},{"animations":[],"initialState":{"affineTransform":[1,0,0,1,0,0],"masksToBounds":false,"rotation":0,"scale":1,"position":{"pointX":2173.5113830566406,"pointY":300.6461181640625},"width":798.97735595703102,"sublayerTransform":[1,0,0,0,0,1,0,0,0,0,1,0,0,0,0,1],"contentsRect":{"y":0,"x":0,"width":1,"height":1},"opacity":1,"edgeAntialiasingMask":251658240,"height":535.707763671875,"hidden":false,"anchorPoint":{"pointX":0.5,"pointY":0.5}},"layers":[{"animations":[],"layers":[],"texturedRectangle":{"isBackgroundTexture":true,"singleTextureOpacity":1,"textureType":5,"textBaseline":0,"textXHeight":0,"isVerticalText":false},"initialState":{"affineTransform":[0.17292741280544968,-0.98493457138046159,0.98493457138046159,0.17292741280544968,0,0],"masksToBounds":false,"rotation":-1.3969952382630173,"scale":1,"position":{"pointX":399.4886779785154,"pointY":267.85388183593744},"width":802,"sublayerTransform":[1,0,0,0,0,1,0,0,0,0,1,0,0,0,0,1],"contentsRect":{"y":0,"x":0,"width":1,"height":1},"opacity":1,"edgeAntialiasingMask":0,"height":539,"hidden":false,"anchorPoint":{"pointX":0.4993907519409484,"pointY":0.50027109121347391}},"texture":"CBDD5B23089DF60DE60F591CF37FF822"}]},{"animations":[],"initialState":{"affineTransform":[1,0,0,1,0,0],"masksToBounds":false,"rotation":0,"scale":1,"position":{"pointX":1383.3723297119141,"pointY":1331.3879547119141},"width":509.25540161132812,"sublayerTransform":[1,0,0,0,0,1,0,0,0,0,1,0,0,0,0,1],"contentsRect":{"y":0,"x":0,"width":1,"height":1},"opacity":1,"edgeAntialiasingMask":251658240,"height":509.25540161132812,"hidden":false,"anchorPoint":{"pointX":0.5,"pointY":0.5}},"layers":[{"animations":[],"layers":[],"texturedRectangle":{"isBackgroundTexture":true,"singleTextureOpacity":1,"textureType":5,"textBaseline":0,"textXHeight":0,"isVerticalText":false},"initialState":{"affineTransform":[1,0,0,1,0,0],"masksToBounds":false,"rotation":0,"scale":1,"position":{"pointX":254.62770080566406,"pointY":254.62770080566406},"width":513,"sublayerTransform":[1,0,0,0,0,1,0,0,0,0,1,0,0,0,0,1],"contentsRect":{"y":0,"x":0,"width":1,"height":1},"opacity":1,"edgeAntialiasingMask":0,"height":513,"hidden":false,"anchorPoint":{"pointX":0.49975113004271748,"pointY":0.4997815881323861}},"texture":"9BE02F6FC5B80C71FE8949B0FC309186"}]},{"animations":[],"initialState":{"affineTransform":[1,0,0,1,0,0],"masksToBounds":false,"rotation":0,"scale":1,"position":{"pointX":440.43731689453125,"pointY":1411.5346069335938},"width":766.8746337890625,"sublayerTransform":[1,0,0,0,0,1,0,0,0,0,1,0,0,0,0,1],"contentsRect":{"y":0,"x":0,"width":1,"height":1},"opacity":1,"edgeAntialiasingMask":251658240,"height":880.4246826171875,"hidden":false,"anchorPoint":{"pointX":0.5,"pointY":0.5}},"layers":[{"animations":[],"layers":[],"texturedRectangle":{"isBackgroundTexture":true,"singleTextureOpacity":1,"textureType":5,"textBaseline":0,"textXHeight":0,"isVerticalText":false},"initialState":{"affineTransform":[1,0,0,1,0,0],"masksToBounds":false,"rotation":0,"scale":1,"position":{"pointX":383.43731689453125,"pointY":440.21234130859375},"width":769,"sublayerTransform":[1,0,0,0,0,1,0,0,0,0,1,0,0,0,0,1],"contentsRect":{"y":0,"x":0,"width":1,"height":1},"opacity":1,"edgeAntialiasingMask":0,"height":883,"hidden":false,"anchorPoint":{"pointX":0.49991848750914336,"pointY":0.50003919245027606}},"texture":"78508608182FAB3EE650F9382A01EC41"}]},{"animations":[],"initialState":{"affineTransform":[1,0,0,1,0,0],"masksToBounds":false,"rotation":0,"scale":1,"position":{"pointX":2044.3170471191406,"pointY":993.87232971191406},"width":558.36602783203125,"sublayerTransform":[1,0,0,0,0,1,0,0,0,0,1,0,0,0,0,1],"contentsRect":{"y":0,"x":0,"width":1,"height":1},"opacity":1,"edgeAntialiasingMask":251658240,"height":509.25540161132812,"hidden":false,"anchorPoint":{"pointX":0.5,"pointY":0.5}},"layers":[{"animations":[],"layers":[],"texturedRectangle":{"isBackgroundTexture":true,"singleTextureOpacity":1,"textureType":5,"textBaseline":0,"textXHeight":0,"isVerticalText":false},"initialState":{"affineTransform":[1,0,0,1,0,0],"masksToBounds":false,"rotation":0,"scale":1,"position":{"pointX":279.18301391601562,"pointY":254.62770080566406},"width":561,"sublayerTransform":[1,0,0,0,0,1,0,0,0,0,1,0,0,0,0,1],"contentsRect":{"y":0,"x":0,"width":1,"height":1},"opacity":1,"edgeAntialiasingMask":0,"height":512,"hidden":false,"anchorPoint":{"pointX":0.49967388078278185,"pointY":0.49975064396858215}},"texture":"B1212B6D950D4391052A9C47C6D0A889"}]},{"animations":[],"initialState":{"affineTransform":[1,0,0,1,0,0],"masksToBounds":false,"rotation":0,"scale":1,"position":{"pointX":-260,"pointY":786},"width":433,"sublayerTransform":[1,0,0,0,0,1,0,0,0,0,1,0,0,0,0,1],"contentsRect":{"y":0,"x":0,"width":1,"height":1},"opacity":1,"edgeAntialiasingMask":251658240,"height":577,"hidden":false,"anchorPoint":{"pointX":0.5,"pointY":0.5}},"layers":[{"animations":[],"layers":[],"texturedRectangle":{"isBackgroundTexture":true,"singleTextureOpacity":1,"textureType":5,"textBaseline":0,"textXHeight":0,"isVerticalText":false},"initialState":{"affineTransform":[1,0,0,1,0,0],"masksToBounds":false,"rotation":0,"scale":1,"position":{"pointX":216.5,"pointY":288.5},"width":436,"sublayerTransform":[1,0,0,0,0,1,0,0,0,0,1,0,0,0,0,1],"contentsRect":{"y":0,"x":0,"width":1,"height":1},"opacity":1,"edgeAntialiasingMask":0,"height":580,"hidden":false,"anchorPoint":{"pointX":0.5,"pointY":0.5}},"texture":"416F62ED9726381F58EB430DB9989F21"}]},{"animations":[],"initialState":{"affineTransform":[1,0,0,1,0,0],"masksToBounds":false,"rotation":0,"scale":1,"position":{"pointX":616.0513916015625,"pointY":1381.0085754394531},"width":1056.32666015625,"sublayerTransform":[1,0,0,0,0,1,0,0,0,0,1,0,0,0,0,1],"contentsRect":{"y":0,"x":0,"width":1,"height":1},"opacity":1,"edgeAntialiasingMask":251658240,"height":708.25836181640625,"hidden":false,"anchorPoint":{"pointX":0.5,"pointY":0.5}},"layers":[{"animations":[],"layers":[],"texturedRectangle":{"isBackgroundTexture":true,"singleTextureOpacity":1,"textureType":5,"textBaseline":0,"textXHeight":0,"isVerticalText":false},"initialState":{"affineTransform":[1,0,0,1,0,0],"masksToBounds":false,"rotation":0,"scale":1,"position":{"pointX":528.163330078125,"pointY":354.12918090820312},"width":1060,"sublayerTransform":[1,0,0,0,0,1,0,0,0,0,1,0,0,0,0,1],"contentsRect":{"y":0,"x":0,"width":1,"height":1},"opacity":1,"edgeAntialiasingMask":0,"height":712,"hidden":false,"anchorPoint":{"pointX":0.50004848264298352,"pointY":0.50001204415653533}},"texture":"ABE537E55E4D3A760C0FDB22C2340556"}]},{"animations":[],"initialState":{"affineTransform":[1,0,0,1,0,0],"masksToBounds":false,"rotation":0,"scale":1,"position":{"pointX":350.04957580566406,"pointY":91.490875244140625},"width":297.421875,"sublayerTransform":[1,0,0,0,0,1,0,0,0,0,1,0,0,0,0,1],"contentsRect":{"y":0,"x":0,"width":1,"height":1},"opacity":1,"edgeAntialiasingMask":251658240,"height":72.79656982421875,"hidden":false,"anchorPoint":{"pointX":0.5,"pointY":0.5}},"layers":[{"animations":[],"layers":[],"texturedRectangle":{"singleTextureOpacity":1,"textXHeight":0.5157470703125,"textBaseline":0.865576426188151,"isBackgroundTexture":true,"isVerticalText":false,"textColor":[0.97254902124404907,0.97254902124404907,0.94901961088180542,1],"textureType":6},"initialState":{"affineTransform":[1,0,0,1,0,0],"masksToBounds":false,"rotation":0,"scale":1,"position":{"pointX":148.7109375,"pointY":36.398284912109375},"width":98,"sublayerTransform":[1,0,0,0,0,1,0,0,0,0,1,0,0,0,0,1],"contentsRect":{"y":0,"x":0,"width":1,"height":1},"opacity":1,"edgeAntialiasingMask":0,"height":48,"hidden":true,"anchorPoint":{"pointX":0.50050587556800064,"pointY":0.36439323425292969}},"texture":"2AF5D14B5C73FB4641568DEFE2E0953C"}]},{"animations":[],"initialState":{"affineTransform":[1,0,0,1,0,0],"masksToBounds":false,"rotation":0,"scale":1,"position":{"pointX":752.7578125,"pointY":122.24868774414061},"width":381.515625,"sublayerTransform":[1,0,0,0,0,1,0,0,0,0,1,0,0,0,0,1],"contentsRect":{"y":0,"x":0,"width":1,"height":1},"opacity":1,"edgeAntialiasingMask":251658240,"height":102.31219482421878,"hidden":false,"anchorPoint":{"pointX":0.5,"pointY":0.5}},"layers":[{"animations":[],"layers":[],"texturedRectangle":{"singleTextureOpacity":1,"textXHeight":0.5802154541015625,"textBaseline":0.86512184143066406,"isBackgroundTexture":true,"isVerticalText":false,"textColor":[0.97254902124404907,0.97254902124404907,0.94901961088180542,1],"textureType":6},"initialState":{"affineTransform":[1,0,0,1,0,0],"masksToBounds":false,"rotation":0,"scale":1,"position":{"pointX":190.7578125,"pointY":51.156097412109403},"width":294,"sublayerTransform":[1,0,0,0,0,1,0,0,0,0,1,0,0,0,0,1],"contentsRect":{"y":0,"x":0,"width":1,"height":1},"opacity":1,"edgeAntialiasingMask":0,"height":32,"hidden":true,"anchorPoint":{"pointX":0.4991762329931973,"pointY":-0.39847850799560547}},"texture":"9303FE48D610EF7CDAFEA4BEE56058C4"}]},{"animations":[],"initialState":{"affineTransform":[1,0,0,1,0,0],"masksToBounds":false,"rotation":0,"scale":1,"position":{"pointX":752.7578125,"pointY":122.24868774414061},"width":381.515625,"sublayerTransform":[1,0,0,0,0,1,0,0,0,0,1,0,0,0,0,1],"contentsRect":{"y":0,"x":0,"width":1,"height":1},"opacity":1,"edgeAntialiasingMask":251658240,"height":102.31219482421878,"hidden":false,"anchorPoint":{"pointX":0.5,"pointY":0.5}},"layers":[{"animations":[],"layers":[],"texturedRectangle":{"singleTextureOpacity":1,"textXHeight":0.50180796030405406,"textBaseline":0.85632159258868246,"isBackgroundTexture":true,"isVerticalText":false,"textColor":[0.97254902124404907,0.97254902124404907,0.94901961088180542,1],"textureType":6},"initialState":{"affineTransform":[1,0,0,1,0,0],"masksToBounds":false,"rotation":0,"scale":1,"position":{"pointX":190.7578125,"pointY":51.156097412109403},"width":374,"sublayerTransform":[1,0,0,0,0,1,0,0,0,0,1,0,0,0,0,1],"contentsRect":{"y":0,"x":0,"width":1,"height":1},"opacity":1,"edgeAntialiasingMask":0,"height":37,"hidden":true,"anchorPoint":{"pointX":0.49935243983957217,"pointY":1.0337483174092061}},"texture":"27B373701DB4D31FC4D592353D6E6AAC"}]},{"animations":[],"initialState":{"affineTransform":[1,0,0,1,0,0],"masksToBounds":false,"rotation":0,"scale":1,"position":{"pointX":812.7109375,"pointY":345.53460693359375},"width":297.421875,"sublayerTransform":[1,0,0,0,0,1,0,0,0,0,1,0,0,0,0,1],"contentsRect":{"y":0,"x":0,"width":1,"height":1},"opacity":1,"edgeAntialiasingMask":251658240,"height":72.79656982421875,"hidden":false,"anchorPoint":{"pointX":0.5,"pointY":0.5}},"layers":[{"animations":[],"layers":[],"texturedRectangle":{"singleTextureOpacity":1,"textXHeight":0.52672041223404253,"textBaseline":0.86364681162732715,"isBackgroundTexture":true,"isVerticalText":false,"textColor":[0.97254902124404907,0.97254902124404907,0.94901961088180542,1],"textureType":6},"initialState":{"affineTransform":[1,0,0,1,0,0],"masksToBounds":false,"rotation":0,"scale":1,"position":{"pointX":148.7109375,"pointY":36.398284912109375},"width":148,"sublayerTransform":[1,0,0,0,0,1,0,0,0,0,1,0,0,0,0,1],"contentsRect":{"y":0,"x":0,"width":1,"height":1},"opacity":1,"edgeAntialiasingMask":0,"height":47,"hidden":true,"anchorPoint":{"pointX":0.498046875,"pointY":0.35180014752327127}},"texture":"F2DAB0D8CC060BFE0FF91E035EADADBA"}]},{"animations":[],"initialState":{"affineTransform":[1,0,0,1,0,0],"masksToBounds":false,"rotation":0,"scale":1,"position":{"pointX":470.2109375,"pointY":695.88351440429688},"width":216.421875,"sublayerTransform":[1,0,0,0,0,1,0,0,0,0,1,0,0,0,0,1],"contentsRect":{"y":0,"x":0,"width":1,"height":1},"opacity":1,"edgeAntialiasingMask":251658240,"height":62.546569824218864,"hidden":false,"anchorPoint":{"pointX":0.5,"pointY":0.5}},"layers":[{"animations":[],"layers":[],"texturedRectangle":{"singleTextureOpacity":1,"textXHeight":0.50926339285714284,"textBaseline":0.87022530691964284,"isBackgroundTexture":true,"isVerticalText":false,"textColor":[0.97254902124404907,0.97254902124404907,0.94901961088180542,1],"textureType":6},"initialState":{"affineTransform":[1,0,0,1,0,0],"masksToBounds":false,"rotation":0,"scale":1,"position":{"pointX":108.2109375,"pointY":31.273284912109489},"width":207,"sublayerTransform":[1,0,0,0,0,1,0,0,0,0,1,0,0,0,0,1],"contentsRect":{"y":0,"x":0,"width":1,"height":1},"opacity":1,"edgeAntialiasingMask":0,"height":35,"hidden":true,"anchorPoint":{"pointX":0.49860356280193235,"pointY":0.36810041155133927}},"texture":"E7B509513C785FFB14F4900734FC5E6C"}]},{"animations":[],"initialState":{"affineTransform":[1,0,0,1,0,0],"masksToBounds":false,"rotation":0,"scale":1,"position":{"pointX":1409.372314453125,"pointY":520.6461181640625},"width":297.421875,"sublayerTransform":[1,0,0,0,0,1,0,0,0,0,1,0,0,0,0,1],"contentsRect":{"y":0,"x":0,"width":1,"height":1},"opacity":1,"edgeAntialiasingMask":251658240,"height":72.79656982421875,"hidden":false,"anchorPoint":{"pointX":0.5,"pointY":0.5}},"layers":[{"animations":[],"layers":[],"texturedRectangle":{"singleTextureOpacity":1,"textXHeight":0.5157470703125,"textBaseline":0.86881065368652344,"isBackgroundTexture":true,"isVerticalText":false,"textColor":[0.97254902124404907,0.97254902124404907,0.94901961088180542,1],"textureType":6},"initialState":{"affineTransform":[1,0,0,1,0,0],"masksToBounds":false,"rotation":0,"scale":1,"position":{"pointX":148.7109375,"pointY":36.398284912109375},"width":237,"sublayerTransform":[1,0,0,0,0,1,0,0,0,0,1,0,0,0,0,1],"contentsRect":{"y":0,"x":0,"width":1,"height":1},"opacity":1,"edgeAntialiasingMask":0,"height":48,"hidden":true,"anchorPoint":{"pointX":0.49524183313554854,"pointY":0.36762746175130206}},"texture":"1D50D4427BE7767B6298F1E7272B7517"}]},{"animations":[],"initialState":{"affineTransform":[1,0,0,1,0,0],"masksToBounds":false,"rotation":0,"scale":1,"position":{"pointX":1232.89453125,"pointY":186.015625},"width":350.9296875,"sublayerTransform":[1,0,0,0,0,1,0,0,0,0,1,0,0,0,0,1],"contentsRect":{"y":0,"x":0,"width":1,"height":1},"opacity":1,"edgeAntialiasingMask":251658240,"height":119.42156982421875,"hidden":false,"anchorPoint":{"pointX":0.5,"pointY":0.5}},"layers":[{"animations":[],"layers":[],"texturedRectangle":{"singleTextureOpacity":1,"textXHeight":0.50146484375,"textBaseline":0.86036799504206729,"isBackgroundTexture":true,"isVerticalText":false,"textColor":[0.97254902124404907,0.97254902124404907,0.94901961088180542,1],"textureType":6},"initialState":{"affineTransform":[1,0,0,1,0,0],"masksToBounds":false,"rotation":0,"scale":1,"position":{"pointX":175.46484375,"pointY":59.710784912109375},"width":237,"sublayerTransform":[1,0,0,0,0,1,0,0,0,0,1,0,0,0,0,1],"contentsRect":{"y":0,"x":0,"width":1,"height":1},"opacity":1,"edgeAntialiasingMask":0,"height":39,"hidden":true,"anchorPoint":{"pointX":0.50166468881856541,"pointY":1.0260416666666667}},"texture":"E1179C3FB2577AB4FB025FB9EB4E6E83"}]},{"animations":[],"initialState":{"affineTransform":[1,0,0,1,0,0],"masksToBounds":false,"rotation":0,"scale":1,"position":{"pointX":1232.89453125,"pointY":186.015625},"width":350.9296875,"sublayerTransform":[1,0,0,0,0,1,0,0,0,0,1,0,0,0,0,1],"contentsRect":{"y":0,"x":0,"width":1,"height":1},"opacity":1,"edgeAntialiasingMask":251658240,"height":119.42156982421875,"hidden":false,"anchorPoint":{"pointX":0.5,"pointY":0.5}},"layers":[{"animations":[],"layers":[],"texturedRectangle":{"singleTextureOpacity":1,"textXHeight":0.57520967371323528,"textBaseline":0.86924564137178306,"isBackgroundTexture":true,"isVerticalText":false,"textColor":[0.97254902124404907,0.97254902124404907,0.94901961088180542,1],"textureType":6},"initialState":{"affineTransform":[1,0,0,1,0,0],"masksToBounds":false,"rotation":0,"scale":1,"position":{"pointX":175.46484375,"pointY":59.710784912109375},"width":346,"sublayerTransform":[1,0,0,0,0,1,0,0,0,0,1,0,0,0,0,1],"contentsRect":{"y":0,"x":0,"width":1,"height":1},"opacity":1,"edgeAntialiasingMask":0,"height":34,"hidden":true,"anchorPoint":{"pointX":0.49969517702312138,"pointY":-0.41130514705882354}},"texture":"0FB273F8C0876C3FC3D36949432391AB"}]},{"animations":[],"initialState":{"affineTransform":[1,0,0,1,0,0],"masksToBounds":false,"rotation":0,"scale":1,"position":{"pointX":1468.7109375,"pointY":863.78622436523438},"width":297.421875,"sublayerTransform":[1,0,0,0,0,1,0,0,0,0,1,0,0,0,0,1],"contentsRect":{"y":0,"x":0,"width":1,"height":1},"opacity":1,"edgeAntialiasingMask":251658240,"height":72.79656982421875,"hidden":false,"anchorPoint":{"pointX":0.5,"pointY":0.5}},"layers":[{"animations":[],"layers":[],"texturedRectangle":{"singleTextureOpacity":1,"textXHeight":0.52672041223404253,"textBaseline":0.86900037400265961,"isBackgroundTexture":true,"isVerticalText":false,"textColor":[0.97254902124404907,0.97254902124404907,0.94901961088180542,1],"textureType":6},"initialState":{"affineTransform":[1,0,0,1,0,0],"masksToBounds":false,"rotation":0,"scale":1,"position":{"pointX":148.7109375,"pointY":36.398284912109375},"width":146,"sublayerTransform":[1,0,0,0,0,1,0,0,0,0,1,0,0,0,0,1],"contentsRect":{"y":0,"x":0,"width":1,"height":1},"opacity":1,"edgeAntialiasingMask":0,"height":47,"hidden":true,"anchorPoint":{"pointX":0.49117080479452052,"pointY":0.35715370989860373}},"texture":"CC4B95A4BE772319D0FA1F96092A5C80"}]},{"animations":[],"initialState":{"affineTransform":[1,0,0,1,0,0],"masksToBounds":false,"rotation":0,"scale":1,"position":{"pointX":1560.7109375,"pointY":331.53460693359375},"width":297.421875,"sublayerTransform":[1,0,0,0,0,1,0,0,0,0,1,0,0,0,0,1],"contentsRect":{"y":0,"x":0,"width":1,"height":1},"opacity":1,"edgeAntialiasingMask":251658240,"height":72.79656982421875,"hidden":false,"anchorPoint":{"pointX":0.5,"pointY":0.5}},"layers":[{"animations":[],"layers":[],"texturedRectangle":{"singleTextureOpacity":1,"textXHeight":0.5157470703125,"textBaseline":0.86648750305175781,"isBackgroundTexture":true,"isVerticalText":false,"textColor":[0.97254902124404907,0.97254902124404907,0.94901961088180542,1],"textureType":6},"initialState":{"affineTransform":[1,0,0,1,0,0],"masksToBounds":false,"rotation":0,"scale":1,"position":{"pointX":148.7109375,"pointY":36.398284912109375},"width":236,"sublayerTransform":[1,0,0,0,0,1,0,0,0,0,1,0,0,0,0,1],"contentsRect":{"y":0,"x":0,"width":1,"height":1},"opacity":1,"edgeAntialiasingMask":0,"height":48,"hidden":true,"anchorPoint":{"pointX":0.49877515889830509,"pointY":0.36530431111653644}},"texture":"D1963322FF6D6EB9958D88884468DCB7"}]}]}}]}